Workbook

Sheet Methodology
A1: ROI Analysis — Methodology
A3: Two metrics are computed for every program x occupation combination (60 programs x 2 occupations = 120 rows):
A5: 1. PAYBACK PERIOD (years) — how long until the degree pays for itself
A6: Basic payback = Total tuition / Annual net salary
A7: Realistic payback = (Total tuition + Total living cost) / Annual net salary
A9: 2. CUMULATIVE ROI (%) — percentage return by year N, using the realistic total investment
A10: N-year ROI = ((N x Annual net salary) - (Total tuition + Total living cost)) / (Total tuition + Total living cost) x 100
A11: Computed at N = 5 years and N = 10 years post-graduation.
A13: SUMMARY STATISTIC: Since each country has 10 sampled programs, the Summary sheet reports the
A14: MEDIAN across those 10 programs, plus the 25th-75th percentile (IQR) to show spread — not just a
A15: single country-level average, which would hide how much results vary by specific program.
A17: KEY ASSUMPTIONS / LIMITATIONS
... A40: Salary and tax data: Graduate_outcomes.xlsx (per-country source citations in that file)

Sheet Tuition_Data
A1: Country | B1: Program | C1: University | D1: Total tuition (USD) | E1: Duration (months) | F1: Total living cost (USD) | G1: Total direct cost (USD)
A2: United States | B2: Business Analytics | C2: MIT | D2: 96884 | E2: 12 | F2: 54120 | G2: 151004
A3: United States | B3: Statistics & Data Science | C3: Stanford University | D3: 70900 | E3: 18 | F3: 90027 | G3: 160927
A4: United States | B4: Data Science | C4: Harvard University | D4: 101256 | E4: 16 | F4: 63245 | G4: 164501
A5: United States | B5: Data Science | C5: University of Pennsylvania | D5: 88250 | E5: 21 | F5: 63534 | G5: 151784
A6: United States | B6: Data Science & Applied Statistics | C6: Cornell University | D6: 73946 | E6: 12 | F6: 39829 | G6: 113775
A7: United States | B7: Statistics & Data Science | C7: Yale University | D7: 78600 | E7: 16 | F7: 58025 | G7: 136625
A8: United States | B8: Data Science | C8: Johns Hopkins University | D8: 103005 | E8: 16 | F8: 49061 | G8: 152066
A9: United States | B9: Statistics & Data Science | C9: University of California, Berkeley | D9: 55285 | E9: 10 | F9: 38472 | G9: 93757
A10: United States | B10: Applied Data Science | C10: University of Chicago | D10: 76608 | E10: 12 | F10: 46297 | G10: 122905
A11: United States | B11: Data Science | C11: Columbia University | D11: 84660 | E11: 16 | F11: 50037 | G11: 134697
A12: United Kingdom | B12: MSc Statistics (Data Science and Machine Learning) | C12: Imperial College London | D12: 53134 | E12: 12 | F12: 29446 | G12: 82580
A13: United Kingdom | B13: MSc in Statistical Science | C13: University of Oxford | D13: 58234 | E13: 12 | F13: 29078 | G13: 87312
... A61: Netherlands | B61: MSc Applied Mathematics — Mathematics of Data Science & AI | C61: University of Twente | D61: 49428 | E61: 24 | F61: 35834 | G61: 85263

Sheet Salary_Data
A1: Country | B1: Occupation | C1: Net_salary (USD)
A2: United States | B2: Data analyst | C2: 56670
A3: United States | B3: Data scientist | C3: 68785
A4: Canada | B4: Data analyst | C4: 43056
A5: Canada | B5: Data scientist | C5: 50856
A6: United Kingdom | B6: Data analyst | C6: 32523
A7: United Kingdom | B7: Data scientist | C7: 44249
A8: Australia | B8: Data analyst | C8: 45435
A9: Australia | B9: Data scientist | C9: 49280
A10: Germany | B10: Data analyst | C10: 41467
A11: Germany | B11: Data scientist | C11: 46310
A12: Netherlands | B12: Data analyst | C12: 42690
A13: Netherlands | B13: Data scientist | C13: 50320

Sheet ROI_Calculations
A1: Country | B1: Program | C1: University | D1: Occupation | E1: Total tuition (USD) | F1: Total direct cost (USD) | G1: Net salary (USD) | H1: Basic payback (years) | I1: Realistic payback (years) | J1: 5yr ROI (%) | K1: 10yr ROI (%)
A2: =Tuition_Data!A2 -> United States | B2: =Tuition_Data!B2 -> Business Analytics | C2: =Tuition_Data!C2 -> MIT | D2: Data analyst | E2: =Tuition_Data!D2 -> 96884 | F2: =Tuition_Data!G2 -> 151004 | G2: =SUMIFS(Salary_Data!$C$2:$C$13,Salary_Data!$A$2:$A$13,A2,Salary_Data!$B$2:$B$13,D2) -> 56670 | H2: =E2/G2 -> 1.7096171 | I2: =F2/G2 -> 2.6646197 | J2: =((5*G2-F2)/F2)*100 -> 87.644036 | K2: =((10*G2-F2)/F2)*100 -> 275.28807
A3: =Tuition_Data!A2 -> United States | B3: =Tuition_Data!B2 -> Business Analytics | C3: =Tuition_Data!C2 -> MIT | D3: Data scientist | E3: =Tuition_Data!D2 -> 96884 | F3: =Tuition_Data!G2 -> 151004 | G3: =SUMIFS(Salary_Data!$C$2:$C$13,Salary_Data!$A$2:$A$13,A3,Salary_Data!$B$2:$B$13,D3) -> 68785 | H3: =E3/G3 -> 1.4085048 | I3: =F3/G3 -> 2.1953042 | J3: =((5*G3-F3)/F3)*100 -> 127.75887 | K3: =((10*G3-F3)/F3)*100 -> 355.51773
A4: =Tuition_Data!A3 -> United States | B4: =Tuition_Data!B3 -> Statistics & Data Science | C4: =Tuition_Data!C3 -> Stanford University | D4: Data analyst | E4: =Tuition_Data!D3 -> 70900 | F4: =Tuition_Data!G3 -> 160927 | G4: =SUMIFS(Salary_Data!$C$2:$C$13,Salary_Data!$A$2:$A$13,A4,Salary_Data!$B$2:$B$13,D4) -> 56670 | H4: =E4/G4 -> 1.2511029 | I4: =F4/G4 -> 2.8397212 | J4: =((5*G4-F4)/F4)*100 -> 76.073623 | K4: =((10*G4-F4)/F4)*100 -> 252.14725
A5: =Tuition_Data!A3 -> United States | B5: =Tuition_Data!B3 -> Statistics & Data Science | C5: =Tuition_Data!C3 -> Stanford University | D5: Data scientist | E5: =Tuition_Data!D3 -> 70900 | F5: =Tuition_Data!G3 -> 160927 | G5: =SUMIFS(Salary_Data!$C$2:$C$13,Salary_Data!$A$2:$A$13,A5,Salary_Data!$B$2:$B$13,D5) -> 68785 | H5: =E5/G5 -> 1.030748 | I5: =F5/G5 -> 2.3395653 | J5: =((5*G5-F5)/F5)*100 -> 113.71491 | K5: =((10*G5-F5)/F5)*100 -> 327.42983
A6: =Tuition_Data!A4 -> United States | B6: =Tuition_Data!B4 -> Data Science | C6: =Tuition_Data!C4 -> Harvard University | D6: Data analyst | E6: =Tuition_Data!D4 -> 101256 | F6: =Tuition_Data!G4 -> 164501 | G6: =SUMIFS(Salary_Data!$C$2:$C$13,Salary_Data!$A$2:$A$13,A6,Salary_Data!$B$2:$B$13,D6) -> 56670 | H6: =E6/G6 -> 1.7867655 | I6: =F6/G6 -> 2.9027881 | J6: =((5*G6-F6)/F6)*100 -> 72.248193 | K6: =((10*G6-F6)/F6)*100 -> 244.49639
A7: =Tuition_Data!A4 -> United States | B7: =Tuition_Data!B4 -> Data Science | C7: =Tuition_Data!C4 -> Harvard University | D7: Data scientist | E7: =Tuition_Data!D4 -> 101256 | F7: =Tuition_Data!G4 -> 164501 | G7: =SUMIFS(Salary_Data!$C$2:$C$13,Salary_Data!$A$2:$A$13,A7,Salary_Data!$B$2:$B$13,D7) -> 68785 | H7: =E7/G7 -> 1.4720651 | I7: =F7/G7 -> 2.3915243 | J7: =((5*G7-F7)/F7)*100 -> 109.07168 | K7: =((10*G7-F7)/F7)*100 -> 318.14335
A8: =Tuition_Data!A5 -> United States | B8: =Tuition_Data!B5 -> Data Science | C8: =Tuition_Data!C5 -> University of Pennsylvania | D8: Data analyst | E8: =Tuition_Data!D5 -> 88250 | F8: =Tuition_Data!G5 -> 151784 | G8: =SUMIFS(Salary_Data!$C$2:$C$13,Salary_Data!$A$2:$A$13,A8,Salary_Data!$B$2:$B$13,D8) -> 56670 | H8: =E8/G8 -> 1.5572613 | I8: =F8/G8 -> 2.6783836 | J8: =((5*G8-F8)/F8)*100 -> 86.679755 | K8: =((10*G8-F8)/F8)*100 -> 273.35951
A9: =Tuition_Data!A5 -> United States | B9: =Tuition_Data!B5 -> Data Science | C9: =Tuition_Data!C5 -> University of Pennsylvania | D9: Data scientist | E9: =Tuition_Data!D5 -> 88250 | F9: =Tuition_Data!G5 -> 151784 | G9: =SUMIFS(Salary_Data!$C$2:$C$13,Salary_Data!$A$2:$A$13,A9,Salary_Data!$B$2:$B$13,D9) -> 68785 | H9: =E9/G9 -> 1.2829832 | I9: =F9/G9 -> 2.2066439 | J9: =((5*G9-F9)/F9)*100 -> 126.58844 | K9: =((10*G9-F9)/F9)*100 -> 353.17688
A10: =Tuition_Data!A6 -> United States | B10: =Tuition_Data!B6 -> Data Science & Applied Statistics | C10: =Tuition_Data!C6 -> Cornell University | D10: Data analyst | E10: =Tuition_Data!D6 -> 73946 | F10: =Tuition_Data!G6 -> 113775 | G10: =SUMIFS(Salary_Data!$C$2:$C$13,Salary_Data!$A$2:$A$13,A10,Salary_Data!$B$2:$B$13,D10) -> 56670 | H10: =E10/G10 -> 1.3048527 | I10: =F10/G10 -> 2.007676 | J10: =((5*G10-F10)/F10)*100 -> 149.04417 | K10: =((10*G10-F10)/F10)*100 -> 398.08833
A11: =Tuition_Data!A6 -> United States | B11: =Tuition_Data!B6 -> Data Science & Applied Statistics | C11: =Tuition_Data!C6 -> Cornell University | D11: Data scientist | E11: =Tuition_Data!D6 -> 73946 | F11: =Tuition_Data!G6 -> 113775 | G11: =SUMIFS(Salary_Data!$C$2:$C$13,Salary_Data!$A$2:$A$13,A11,Salary_Data!$B$2:$B$13,D11) -> 68785 | H11: =E11/G11 -> 1.0750309 | I11: =F11/G11 -> 1.654067 | J11: =((5*G11-F11)/F11)*100 -> 202.28521 | K11: =((10*G11-F11)/F11)*100 -> 504.57042
A12: =Tuition_Data!A7 -> United States | B12: =Tuition_Data!B7 -> Statistics & Data Science | C12: =Tuition_Data!C7 -> Yale University | D12: Data analyst | E12: =Tuition_Data!D7 -> 78600 | F12: =Tuition_Data!G7 -> 136625 | G12: =SUMIFS(Salary_Data!$C$2:$C$13,Salary_Data!$A$2:$A$13,A12,Salary_Data!$B$2:$B$13,D12) -> 56670 | H12: =E12/G12 -> 1.3869772 | I12: =F12/G12 -> 2.4108876 | J12: =((5*G12-F12)/F12)*100 -> 107.3925 | K12: =((10*G12-F12)/F12)*100 -> 314.785
A13: =Tuition_Data!A7 -> United States | B13: =Tuition_Data!B7 -> Statistics & Data Science | C13: =Tuition_Data!C7 -> Yale University | D13: Data scientist | E13: =Tuition_Data!D7 -> 78600 | F13: =Tuition_Data!G7 -> 136625 | G13: =SUMIFS(Salary_Data!$C$2:$C$13,Salary_Data!$A$2:$A$13,A13,Salary_Data!$B$2:$B$13,D13) -> 68785 | H13: =E13/G13 -> 1.142691 | I13: =F13/G13 -> 1.9862615 | J13: =((5*G13-F13)/F13)*100 -> 151.72919 | K13: =((10*G13-F13)/F13)*100 -> 403.45837
A14: =Tuition_Data!A8 -> United States | B14: =Tuition_Data!B8 -> Data Science | C14: =Tuition_Data!C8 -> Johns Hopkins University | D14: Data analyst | E14: =Tuition_Data!D8 -> 103005 | F14: =Tuition_Data!G8 -> 152066 | G14: =SUMIFS(Salary_Data!$C$2:$C$13,Salary_Data!$A$2:$A$13,A14,Salary_Data!$B$2:$B$13,D14) -> 56670 | H14: =E14/G14 -> 1.8176284 | I14: =F14/G14 -> 2.6833598 | J14: =((5*G14-F14)/F14)*100 -> 86.333566 | K14: =((10*G14-F14)/F14)*100 -> 272.66713
A15: =Tuition_Data!A8 -> United States | B15: =Tuition_Data!B8 -> Data Science | C15: =Tuition_Data!C8 -> Johns Hopkins University | D15: Data scientist | E15: =Tuition_Data!D8 -> 103005 | F15: =Tuition_Data!G8 -> 152066 | G15: =SUMIFS(Salary_Data!$C$2:$C$13,Salary_Data!$A$2:$A$13,A15,Salary_Data!$B$2:$B$13,D15) -> 68785 | H15: =E15/G15 -> 1.4974922 | I15: =F15/G15 -> 2.2107436 | J15: =((5*G15-F15)/F15)*100 -> 126.16824 | K15: =((10*G15-F15)/F15)*100 -> 352.33649
A16: =Tuition_Data!A9 -> United States | B16: =Tuition_Data!B9 -> Statistics & Data Science | C16: =Tuition_Data!C9 -> University of California, Berkeley | D16: Data analyst | E16: =Tuition_Data!D9 -> 55285 | F16: =Tuition_Data!G9 -> 93757 | G16: =SUMIFS(Salary_Data!$C$2:$C$13,Salary_Data!$A$2:$A$13,A16,Salary_Data!$B$2:$B$13,D16) -> 56670 | H16: =E16/G16 -> 0.97556026 | I16: =F16/G16 -> 1.654438 | J16: =((5*G16-F16)/F16)*100 -> 202.21743 | K16: =((10*G16-F16)/F16)*100 -> 504.43487
A17: =Tuition_Data!A9 -> United States | B17: =Tuition_Data!B9 -> Statistics & Data Science | C17: =Tuition_Data!C9 -> University of California, Berkeley | D17: Data scientist | E17: =Tuition_Data!D9 -> 55285 | F17: =Tuition_Data!G9 -> 93757 | G17: =SUMIFS(Salary_Data!$C$2:$C$13,Salary_Data!$A$2:$A$13,A17,Salary_Data!$B$2:$B$13,D17) -> 68785 | H17: =E17/G17 -> 0.80373628 | I17: =F17/G17 -> 1.3630443 | J17: =((5*G17-F17)/F17)*100 -> 266.82594 | K17: =((10*G17-F17)/F17)*100 -> 633.65189
A18: =Tuition_Data!A10 -> United States | B18: =Tuition_Data!B10 -> Applied Data Science | C18: =Tuition_Data!C10 -> University of Chicago | D18: Data analyst | E18: =Tuition_Data!D10 -> 76608 | F18: =Tuition_Data!G10 -> 122905 | G18: =SUMIFS(Salary_Data!$C$2:$C$13,Salary_Data!$A$2:$A$13,A18,Salary_Data!$B$2:$B$13,D18) -> 56670 | H18: =E18/G18 -> 1.3518264 | I18: =F18/G18 -> 2.1687842 | J18: =((5*G18-F18)/F18)*100 -> 130.54392 | K18: =((10*G18-F18)/F18)*100 -> 361.08783
A19: =Tuition_Data!A10 -> United States | B19: =Tuition_Data!B10 -> Applied Data Science | C19: =Tuition_Data!C10 -> University of Chicago | D19: Data scientist | E19: =Tuition_Data!D10 -> 76608 | F19: =Tuition_Data!G10 -> 122905 | G19: =SUMIFS(Salary_Data!$C$2:$C$13,Salary_Data!$A$2:$A$13,A19,Salary_Data!$B$2:$B$13,D19) -> 68785 | H19: =E19/G19 -> 1.1137312 | I19: =F19/G19 -> 1.7867994 | J19: =((5*G19-F19)/F19)*100 -> 179.82995 | K19: =((10*G19-F19)/F19)*100 -> 459.6599
A20: =Tuition_Data!A11 -> United States | B20: =Tuition_Data!B11 -> Data Science | C20: =Tuition_Data!C11 -> Columbia University | D20: Data analyst | E20: =Tuition_Data!D11 -> 84660 | F20: =Tuition_Data!G11 -> 134697 | G20: =SUMIFS(Salary_Data!$C$2:$C$13,Salary_Data!$A$2:$A$13,A20,Salary_Data!$B$2:$B$13,D20) -> 56670 | H20: =E20/G20 -> 1.4939121 | I20: =F20/G20 -> 2.3768661 | J20: =((5*G20-F20)/F20)*100 -> 110.36103 | K20: =((10*G20-F20)/F20)*100 -> 320.72207
A21: =Tuition_Data!A11 -> United States | B21: =Tuition_Data!B11 -> Data Science | C21: =Tuition_Data!C11 -> Columbia University | D21: Data scientist | E21: =Tuition_Data!D11 -> 84660 | F21: =Tuition_Data!G11 -> 134697 | G21: =SUMIFS(Salary_Data!$C$2:$C$13,Salary_Data!$A$2:$A$13,A21,Salary_Data!$B$2:$B$13,D21) -> 68785 | H21: =E21/G21 -> 1.2307916 | I21: =F21/G21 -> 1.9582322 | J21: =((5*G21-F21)/F21)*100 -> 155.33234 | K21: =((10*G21-F21)/F21)*100 -> 410.66468
A22: =Tuition_Data!A12 -> United Kingdom | B22: =Tuition_Data!B12 -> MSc Statistics (Data Science and Machine Learning) | C22: =Tuition_Data!C12 -> Imperial College London | D22: Data analyst | E22: =Tuition_Data!D12 -> 53134 | F22: =Tuition_Data!G12 -> 82580 | G22: =SUMIFS(Salary_Data!$C$2:$C$13,Salary_Data!$A$2:$A$13,A22,Salary_Data!$B$2:$B$13,D22) -> 32523 | H22: =E22/G22 -> 1.6337361 | I22: =F22/G22 -> 2.5391262 | J22: =((5*G22-F22)/F22)*100 -> 96.91814 | K22: =((10*G22-F22)/F22)*100 -> 293.83628
A23: =Tuition_Data!A12 -> United Kingdom | B23: =Tuition_Data!B12 -> MSc Statistics (Data Science and Machine Learning) | C23: =Tuition_Data!C12 -> Imperial College London | D23: Data scientist | E23: =Tuition_Data!D12 -> 53134 | F23: =Tuition_Data!G12 -> 82580 | G23: =SUMIFS(Salary_Data!$C$2:$C$13,Salary_Data!$A$2:$A$13,A23,Salary_Data!$B$2:$B$13,D23) -> 44249 | H23: =E23/G23 -> 1.2007955 | I23: =F23/G23 -> 1.8662569 | J23: =((5*G23-F23)/F23)*100 -> 167.91596 | K23: =((10*G23-F23)/F23)*100 -> 435.83192
A24: =Tuition_Data!A13 -> United Kingdom | B24: =Tuition_Data!B13 -> MSc in Statistical Science | C24: =Tuition_Data!C13 -> University of Oxford | D24: Data analyst | E24: =Tuition_Data!D13 -> 58234 | F24: =Tuition_Data!G13 -> 87312 | G24: =SUMIFS(Salary_Data!$C$2:$C$13,Salary_Data!$A$2:$A$13,A24,Salary_Data!$B$2:$B$13,D24) -> 32523 | H24: =E24/G24 -> 1.7905482 | I24: =F24/G24 -> 2.6846232 | J24: =((5*G24-F24)/F24)*100 -> 86.245877 | K24: =((10*G24-F24)/F24)*100 -> 272.49175
A25: =Tuition_Data!A13 -> United Kingdom | B25: =Tuition_Data!B13 -> MSc in Statistical Science | C25: =Tuition_Data!C13 -> University of Oxford | D25: Data scientist | E25: =Tuition_Data!D13 -> 58234 | F25: =Tuition_Data!G13 -> 87312 | G25: =SUMIFS(Salary_Data!$C$2:$C$13,Salary_Data!$A$2:$A$13,A25,Salary_Data!$B$2:$B$13,D25) -> 44249 | H25: =E25/G25 -> 1.3160523 | I25: =F25/G25 -> 1.9731971 | J25: =((5*G25-F25)/F25)*100 -> 153.39587 | K25: =((10*G25-F25)/F25)*100 -> 406.79174
A26: =Tuition_Data!A14 -> United Kingdom | B26: =Tuition_Data!B14 -> MPhil in Data Intensive Science | C26: =Tuition_Data!C14 -> University of Cambridge | D26: Data analyst | E26: =Tuition_Data!D14 -> 52383 | F26: =Tuition_Data!G14 -> 75283 | G26: =SUMIFS(Salary_Data!$C$2:$C$13,Salary_Data!$A$2:$A$13,A26,Salary_Data!$B$2:$B$13,D26) -> 32523 | H26: =E26/G26 -> 1.6106448 | I26: =F26/G26 -> 2.3147619 | J26: =((5*G26-F26)/F26)*100 -> 116.00494 | K26: =((10*G26-F26)/F26)*100 -> 332.00988
A27: =Tuition_Data!A14 -> United Kingdom | B27: =Tuition_Data!B14 -> MPhil in Data Intensive Science | C27: =Tuition_Data!C14 -> University of Cambridge | D27: Data scientist | E27: =Tuition_Data!D14 -> 52383 | F27: =Tuition_Data!G14 -> 75283 | G27: =SUMIFS(Salary_Data!$C$2:$C$13,Salary_Data!$A$2:$A$13,A27,Salary_Data!$B$2:$B$13,D27) -> 44249 | H27: =E27/G27 -> 1.1838234 | I27: =F27/G27 -> 1.7013492 | J27: =((5*G27-F27)/F27)*100 -> 193.88441 | K27: =((10*G27-F27)/F27)*100 -> 487.76882
A28: =Tuition_Data!A15 -> United Kingdom | B28: =Tuition_Data!B15 -> Data Science MSc | C28: =Tuition_Data!C15 -> UCL | D28: Data analyst | E28: =Tuition_Data!D15 -> 62189 | F28: =Tuition_Data!G15 -> 89856 | G28: =SUMIFS(Salary_Data!$C$2:$C$13,Salary_Data!$A$2:$A$13,A28,Salary_Data!$B$2:$B$13,D28) -> 32523 | H28: =E28/G28 -> 1.9121545 | I28: =F28/G28 -> 2.7628448 | J28: =((5*G28-F28)/F28)*100 -> 80.97289 | K28: =((10*G28-F28)/F28)*100 -> 261.94578
A29: =Tuition_Data!A15 -> United Kingdom | B29: =Tuition_Data!B15 -> Data Science MSc | C29: =Tuition_Data!C15 -> UCL | D29: Data scientist | E29: =Tuition_Data!D15 -> 62189 | F29: =Tuition_Data!G15 -> 89856 | G29: =SUMIFS(Salary_Data!$C$2:$C$13,Salary_Data!$A$2:$A$13,A29,Salary_Data!$B$2:$B$13,D29) -> 44249 | H29: =E29/G29 -> 1.4054329 | I29: =F29/G29 -> 2.03069 | J29: =((5*G29-F29)/F29)*100 -> 146.22173 | K29: =((10*G29-F29)/F29)*100 -> 392.44347
A30: =Tuition_Data!A16 -> United Kingdom | B30: =Tuition_Data!B16 -> Data Science MSc | C30: =Tuition_Data!C16 -> University of Edinburgh | D30: Data analyst | E30: =Tuition_Data!D16 -> 54465 | F30: =Tuition_Data!G16 -> 80140 | G30: =SUMIFS(Salary_Data!$C$2:$C$13,Salary_Data!$A$2:$A$13,A30,Salary_Data!$B$2:$B$13,D30) -> 32523 | H30: =E30/G30 -> 1.674661 | I30: =F30/G30 -> 2.4641023 | J30: =((5*G30-F30)/F30)*100 -> 102.91365 | K30: =((10*G30-F30)/F30)*100 -> 305.8273
A31: =Tuition_Data!A16 -> United Kingdom | B31: =Tuition_Data!B16 -> Data Science MSc | C31: =Tuition_Data!C16 -> University of Edinburgh | D31: Data scientist | E31: =Tuition_Data!D16 -> 54465 | F31: =Tuition_Data!G16 -> 80140 | G31: =SUMIFS(Salary_Data!$C$2:$C$13,Salary_Data!$A$2:$A$13,A31,Salary_Data!$B$2:$B$13,D31) -> 44249 | H31: =E31/G31 -> 1.2308753 | I31: =F31/G31 -> 1.8111144 | J31: =((5*G31-F31)/F31)*100 -> 176.07312 | K31: =((10*G31-F31)/F31)*100 -> 452.14624
A32: =Tuition_Data!A17 -> United Kingdom | B32: =Tuition_Data!B17 -> Data Science MSc | C32: =Tuition_Data!C17 -> King's College London | D32: Data analyst | E32: =Tuition_Data!D17 -> 53866 | F32: =Tuition_Data!G17 -> 83184 | G32: =SUMIFS(Salary_Data!$C$2:$C$13,Salary_Data!$A$2:$A$13,A32,Salary_Data!$B$2:$B$13,D32) -> 32523 | H32: =E32/G32 -> 1.6562433 | I32: =F32/G32 -> 2.5576976 | J32: =((5*G32-F32)/F32)*100 -> 95.488315 | K32: =((10*G32-F32)/F32)*100 -> 290.97663
A33: =Tuition_Data!A17 -> United Kingdom | B33: =Tuition_Data!B17 -> Data Science MSc | C33: =Tuition_Data!C17 -> King's College London | D33: Data scientist | E33: =Tuition_Data!D17 -> 53866 | F33: =Tuition_Data!G17 -> 83184 | G33: =SUMIFS(Salary_Data!$C$2:$C$13,Salary_Data!$A$2:$A$13,A33,Salary_Data!$B$2:$B$13,D33) -> 44249 | H33: =E33/G33 -> 1.2173382 | I33: =F33/G33 -> 1.8799069 | J33: =((5*G33-F33)/F33)*100 -> 165.97062 | K33: =((10*G33-F33)/F33)*100 -> 431.94124
A34: =Tuition_Data!A18 -> United Kingdom | B34: =Tuition_Data!B18 -> MSc Data Science (Computer Science Data Informatics) | C34: =Tuition_Data!C18 -> University of Manchester | D34: Data analyst | E34: =Tuition_Data!D18 -> 46875 | F34: =Tuition_Data!G18 -> 72129 | G34: =SUMIFS(Salary_Data!$C$2:$C$13,Salary_Data!$A$2:$A$13,A34,Salary_Data!$B$2:$B$13,D34) -> 32523 | H34: =E34/G34 -> 1.4412877 | I34: =F34/G34 -> 2.2177843 | J34: =((5*G34-F34)/F34)*100 -> 125.45023 | K34: =((10*G34-F34)/F34)*100 -> 350.90047
A35: =Tuition_Data!A18 -> United Kingdom | B35: =Tuition_Data!B18 -> MSc Data Science (Computer Science Data Informatics) | C35: =Tuition_Data!C18 -> University of Manchester | D35: Data scientist | E35: =Tuition_Data!D18 -> 46875 | F35: =Tuition_Data!G18 -> 72129 | G35: =SUMIFS(Salary_Data!$C$2:$C$13,Salary_Data!$A$2:$A$13,A35,Salary_Data!$B$2:$B$13,D35) -> 44249 | H35: =E35/G35 -> 1.059346 | I35: =F35/G35 -> 1.6300707 | J35: =((5*G35-F35)/F35)*100 -> 206.73516 | K35: =((10*G35-F35)/F35)*100 -> 513.47031
A36: =Tuition_Data!A19 -> United Kingdom | B36: =Tuition_Data!B19 -> MSc Data Science | C36: =Tuition_Data!C19 -> University of Bristol | D36: Data analyst | E36: =Tuition_Data!D19 -> 48606 | F36: =Tuition_Data!G19 -> 79394 | G36: =SUMIFS(Salary_Data!$C$2:$C$13,Salary_Data!$A$2:$A$13,A36,Salary_Data!$B$2:$B$13,D36) -> 32523 | H36: =E36/G36 -> 1.4945116 | I36: =F36/G36 -> 2.4411647 | J36: =((5*G36-F36)/F36)*100 -> 104.82026 | K36: =((10*G36-F36)/F36)*100 -> 309.64053
A37: =Tuition_Data!A19 -> United Kingdom | B37: =Tuition_Data!B19 -> MSc Data Science | C37: =Tuition_Data!C19 -> University of Bristol | D37: Data scientist | E37: =Tuition_Data!D19 -> 48606 | F37: =Tuition_Data!G19 -> 79394 | G37: =SUMIFS(Salary_Data!$C$2:$C$13,Salary_Data!$A$2:$A$13,A37,Salary_Data!$B$2:$B$13,D37) -> 44249 | H37: =E37/G37 -> 1.0984655 | I37: =F37/G37 -> 1.7942552 | J37: =((5*G37-F37)/F37)*100 -> 178.66715 | K37: =((10*G37-F37)/F37)*100 -> 457.33431
A38: =Tuition_Data!A20 -> United Kingdom | B38: =Tuition_Data!B20 -> MSc Data Science | C38: =Tuition_Data!C20 -> London School of Economics and Political Science (LSE) | D38: Data analyst | E38: =Tuition_Data!D20 -> 53134 | F38: =Tuition_Data!G20 -> 78936 | G38: =SUMIFS(Salary_Data!$C$2:$C$13,Salary_Data!$A$2:$A$13,A38,Salary_Data!$B$2:$B$13,D38) -> 32523 | H38: =E38/G38 -> 1.6337361 | I38: =F38/G38 -> 2.4270824 | J38: =((5*G38-F38)/F38)*100 -> 106.00867 | K38: =((10*G38-F38)/F38)*100 -> 312.01733
A39: =Tuition_Data!A20 -> United Kingdom | B39: =Tuition_Data!B20 -> MSc Data Science | C39: =Tuition_Data!C20 -> London School of Economics and Political Science (LSE) | D39: Data scientist | E39: =Tuition_Data!D20 -> 53134 | F39: =Tuition_Data!G20 -> 78936 | G39: =SUMIFS(Salary_Data!$C$2:$C$13,Salary_Data!$A$2:$A$13,A39,Salary_Data!$B$2:$B$13,D39) -> 44249 | H39: =E39/G39 -> 1.2007955 | I39: =F39/G39 -> 1.7839047 | J39: =((5*G39-F39)/F39)*100 -> 180.28403 | K39: =((10*G39-F39)/F39)*100 -> 460.56806
A40: =Tuition_Data!A21 -> United Kingdom | B40: =Tuition_Data!B21 -> Statistics with Data Science MSc | C40: =Tuition_Data!C21 -> University of Warwick | D40: Data analyst | E40: =Tuition_Data!D21 -> 49884 | F40: =Tuition_Data!G21 -> 69071 | G40: =SUMIFS(Salary_Data!$C$2:$C$13,Salary_Data!$A$2:$A$13,A40,Salary_Data!$B$2:$B$13,D40) -> 32523 | H40: =E40/G40 -> 1.5338068 | I40: =F40/G40 -> 2.1237586 | J40: =((5*G40-F40)/F40)*100 -> 135.43166 | K40: =((10*G40-F40)/F40)*100 -> 370.86331
A41: =Tuition_Data!A21 -> United Kingdom | B41: =Tuition_Data!B21 -> Statistics with Data Science MSc | C41: =Tuition_Data!C21 -> University of Warwick | D41: Data scientist | E41: =Tuition_Data!D21 -> 49884 | F41: =Tuition_Data!G21 -> 69071 | G41: =SUMIFS(Salary_Data!$C$2:$C$13,Salary_Data!$A$2:$A$13,A41,Salary_Data!$B$2:$B$13,D41) -> 44249 | H41: =E41/G41 -> 1.1273475 | I41: =F41/G41 -> 1.5609618 | J41: =((5*G41-F41)/F41)*100 -> 220.31533 | K41: =((10*G41-F41)/F41)*100 -> 540.63066
A42: =Tuition_Data!A22 -> Canada | B42: =Tuition_Data!B22 -> Master of Management in Analytics | C42: =Tuition_Data!C22 -> McGill University | D42: Data analyst | E42: =Tuition_Data!D22 -> 58254 | F42: =Tuition_Data!G22 -> 73232 | G42: =SUMIFS(Salary_Data!$C$2:$C$13,Salary_Data!$A$2:$A$13,A42,Salary_Data!$B$2:$B$13,D42) -> 43056 | H42: =E42/G42 -> 1.3529822 | I42: =F42/G42 -> 1.7008547 | J42: =((5*G42-F42)/F42)*100 -> 193.96985 | K42: =((10*G42-F42)/F42)*100 -> 487.9397
A43: =Tuition_Data!A22 -> Canada | B43: =Tuition_Data!B22 -> Master of Management in Analytics | C43: =Tuition_Data!C22 -> McGill University | D43: Data scientist | E43: =Tuition_Data!D22 -> 58254 | F43: =Tuition_Data!G22 -> 73232 | G43: =SUMIFS(Salary_Data!$C$2:$C$13,Salary_Data!$A$2:$A$13,A43,Salary_Data!$B$2:$B$13,D43) -> 50856 | H43: =E43/G43 -> 1.1454696 | I43: =F43/G43 -> 1.4399874 | J43: =((5*G43-F43)/F43)*100 -> 247.22526 | K43: =((10*G43-F43)/F43)*100 -> 594.45051
A44: =Tuition_Data!A23 -> Canada | B44: =Tuition_Data!B23 -> MSc in Applied Computing — Data Science | C44: =Tuition_Data!C23 -> University of Toronto | D44: Data analyst | E44: =Tuition_Data!D23 -> 63897 | F44: =Tuition_Data!G23 -> 91805 | G44: =SUMIFS(Salary_Data!$C$2:$C$13,Salary_Data!$A$2:$A$13,A44,Salary_Data!$B$2:$B$13,D44) -> 43056 | H44: =E44/G44 -> 1.484044 | I44: =F44/G44 -> 2.1322232 | J44: =((5*G44-F44)/F44)*100 -> 134.49703 | K44: =((10*G44-F44)/F44)*100 -> 368.99406
A45: =Tuition_Data!A23 -> Canada | B45: =Tuition_Data!B23 -> MSc in Applied Computing — Data Science | C45: =Tuition_Data!C23 -> University of Toronto | D45: Data scientist | E45: =Tuition_Data!D23 -> 63897 | F45: =Tuition_Data!G23 -> 91805 | G45: =SUMIFS(Salary_Data!$C$2:$C$13,Salary_Data!$A$2:$A$13,A45,Salary_Data!$B$2:$B$13,D45) -> 50856 | H45: =E45/G45 -> 1.2564299 | I45: =F45/G45 -> 1.8051951 | J45: =((5*G45-F45)/F45)*100 -> 176.97838 | K45: =((10*G45-F45)/F45)*100 -> 453.95676
A46: =Tuition_Data!A24 -> Canada | B46: =Tuition_Data!B24 -> Master of Data Science — Vancouver | C46: =Tuition_Data!C24 -> University of British Columbia | D46: Data analyst | E46: =Tuition_Data!D24 -> 42410 | F46: =Tuition_Data!G24 -> 64477 | G46: =SUMIFS(Salary_Data!$C$2:$C$13,Salary_Data!$A$2:$A$13,A46,Salary_Data!$B$2:$B$13,D46) -> 43056 | H46: =E46/G46 -> 0.98499628 | I46: =F46/G46 -> 1.4975149 | J46: =((5*G46-F46)/F46)*100 -> 233.8865 | K46: =((10*G46-F46)/F46)*100 -> 567.773
A47: =Tuition_Data!A24 -> Canada | B47: =Tuition_Data!B24 -> Master of Data Science — Vancouver | C47: =Tuition_Data!C24 -> University of British Columbia | D47: Data scientist | E47: =Tuition_Data!D24 -> 42410 | F47: =Tuition_Data!G24 -> 64477 | G47: =SUMIFS(Salary_Data!$C$2:$C$13,Salary_Data!$A$2:$A$13,A47,Salary_Data!$B$2:$B$13,D47) -> 50856 | H47: =E47/G47 -> 0.83392323 | I47: =F47/G47 -> 1.2678347 | J47: =((5*G47-F47)/F47)*100 -> 294.37319 | K47: =((10*G47-F47)/F47)*100 -> 688.74637
A48: =Tuition_Data!A25 -> Canada | B48: =Tuition_Data!B25 -> Master of Management Analytics | C48: =Tuition_Data!C25 -> University of Alberta | D48: Data analyst | E48: =Tuition_Data!D25 -> 42574 | F48: =Tuition_Data!G25 -> 61132 | G48: =SUMIFS(Salary_Data!$C$2:$C$13,Salary_Data!$A$2:$A$13,A48,Salary_Data!$B$2:$B$13,D48) -> 43056 | H48: =E48/G48 -> 0.98880528 | I48: =F48/G48 -> 1.4198253 | J48: =((5*G48-F48)/F48)*100 -> 252.15599 | K48: =((10*G48-F48)/F48)*100 -> 604.31198
A49: =Tuition_Data!A25 -> Canada | B49: =Tuition_Data!B25 -> Master of Management Analytics | C49: =Tuition_Data!C25 -> University of Alberta | D49: Data scientist | E49: =Tuition_Data!D25 -> 42574 | F49: =Tuition_Data!G25 -> 61132 | G49: =SUMIFS(Salary_Data!$C$2:$C$13,Salary_Data!$A$2:$A$13,A49,Salary_Data!$B$2:$B$13,D49) -> 50856 | H49: =E49/G49 -> 0.83714803 | I49: =F49/G49 -> 1.2020607 | J49: =((5*G49-F49)/F49)*100 -> 315.95237 | K49: =((10*G49-F49)/F49)*100 -> 731.90473
A50: =Tuition_Data!A26 -> Canada | B50: =Tuition_Data!B26 -> Master of Data Science and Artificial Intelligence — Co-op | C50: =Tuition_Data!C26 -> University of Waterloo | D50: Data analyst | E50: =Tuition_Data!D26 -> 40054 | F50: =Tuition_Data!G26 -> 71031 | G50: =SUMIFS(Salary_Data!$C$2:$C$13,Salary_Data!$A$2:$A$13,A50,Salary_Data!$B$2:$B$13,D50) -> 43056 | H50: =E50/G50 -> 0.93027685 | I50: =F50/G50 -> 1.6497352 | J50: =((5*G50-F50)/F50)*100 -> 203.07894 | K50: =((10*G50-F50)/F50)*100 -> 506.15787
A51: =Tuition_Data!A26 -> Canada | B51: =Tuition_Data!B26 -> Master of Data Science and Artificial Intelligence — Co-op | C51: =Tuition_Data!C26 -> University of Waterloo | D51: Data scientist | E51: =Tuition_Data!D26 -> 40054 | F51: =Tuition_Data!G26 -> 71031 | G51: =SUMIFS(Salary_Data!$C$2:$C$13,Salary_Data!$A$2:$A$13,A51,Salary_Data!$B$2:$B$13,D51) -> 50856 | H51: =E51/G51 -> 0.78759635 | I51: =F51/G51 -> 1.3967084 | J51: =((5*G51-F51)/F51)*100 -> 257.98454 | K51: =((10*G51-F51)/F51)*100 -> 615.96908
A52: =Tuition_Data!A27 -> Canada | B52: =Tuition_Data!B27 -> Master of Data Analytics | C52: =Tuition_Data!C27 -> Western University | D52: Data analyst | E52: =Tuition_Data!D27 -> 43300 | F52: =Tuition_Data!G27 -> 67943 | G52: =SUMIFS(Salary_Data!$C$2:$C$13,Salary_Data!$A$2:$A$13,A52,Salary_Data!$B$2:$B$13,D52) -> 43056 | H52: =E52/G52 -> 1.005667 | I52: =F52/G52 -> 1.5780147 | J52: =((5*G52-F52)/F52)*100 -> 216.85383 | K52: =((10*G52-F52)/F52)*100 -> 533.70767
A53: =Tuition_Data!A27 -> Canada | B53: =Tuition_Data!B27 -> Master of Data Analytics | C53: =Tuition_Data!C27 -> Western University | D53: Data scientist | E53: =Tuition_Data!D27 -> 43300 | F53: =Tuition_Data!G27 -> 67943 | G53: =SUMIFS(Salary_Data!$C$2:$C$13,Salary_Data!$A$2:$A$13,A53,Salary_Data!$B$2:$B$13,D53) -> 50856 | H53: =E53/G53 -> 0.85142363 | I53: =F53/G53 -> 1.3359879 | J53: =((5*G53-F53)/F53)*100 -> 274.25489 | K53: =((10*G53-F53)/F53)*100 -> 648.50978
A54: =Tuition_Data!A28 -> Canada | B54: =Tuition_Data!B28 -> MSc Computer Science — Machine Learning, internship option | C54: =Tuition_Data!C28 -> Université de Montréal | D54: Data analyst | E54: =Tuition_Data!D28 -> 24840 | F54: =Tuition_Data!G28 -> 54352 | G54: =SUMIFS(Salary_Data!$C$2:$C$13,Salary_Data!$A$2:$A$13,A54,Salary_Data!$B$2:$B$13,D54) -> 43056 | H54: =E54/G54 -> 0.57692308 | I54: =F54/G54 -> 1.262356 | J54: =((5*G54-F54)/F54)*100 -> 296.08478 | K54: =((10*G54-F54)/F54)*100 -> 692.16956
A55: =Tuition_Data!A28 -> Canada | B55: =Tuition_Data!B28 -> MSc Computer Science — Machine Learning, internship option | C55: =Tuition_Data!C28 -> Université de Montréal | D55: Data scientist | E55: =Tuition_Data!D28 -> 24840 | F55: =Tuition_Data!G28 -> 54352 | G55: =SUMIFS(Salary_Data!$C$2:$C$13,Salary_Data!$A$2:$A$13,A55,Salary_Data!$B$2:$B$13,D55) -> 50856 | H55: =E55/G55 -> 0.48843794 | I55: =F55/G55 -> 1.0687431 | J55: =((5*G55-F55)/F55)*100 -> 367.83927 | K55: =((10*G55-F55)/F55)*100 -> 835.67854
A56: =Tuition_Data!A29 -> Canada | B56: =Tuition_Data!B29 -> Master of Management in AI and Analytics | C56: =Tuition_Data!C29 -> McMaster University | D56: Data analyst | E56: =Tuition_Data!D29 -> 46122 | F56: =Tuition_Data!G29 -> 75323 | G56: =SUMIFS(Salary_Data!$C$2:$C$13,Salary_Data!$A$2:$A$13,A56,Salary_Data!$B$2:$B$13,D56) -> 43056 | H56: =E56/G56 -> 1.0712096 | I56: =F56/G56 -> 1.7494194 | J56: =((5*G56-F56)/F56)*100 -> 185.80912 | K56: =((10*G56-F56)/F56)*100 -> 471.61823
A57: =Tuition_Data!A29 -> Canada | B57: =Tuition_Data!B29 -> Master of Management in AI and Analytics | C57: =Tuition_Data!C29 -> McMaster University | D57: Data scientist | E57: =Tuition_Data!D29 -> 46122 | F57: =Tuition_Data!G29 -> 75323 | G57: =SUMIFS(Salary_Data!$C$2:$C$13,Salary_Data!$A$2:$A$13,A57,Salary_Data!$B$2:$B$13,D57) -> 50856 | H57: =E57/G57 -> 0.90691364 | I57: =F57/G57 -> 1.4811035 | J57: =((5*G57-F57)/F57)*100 -> 237.58613 | K57: =((10*G57-F57)/F57)*100 -> 575.17226
A58: =Tuition_Data!A30 -> Canada | B58: =Tuition_Data!B30 -> Full-time Master of Management Analytics | C58: =Tuition_Data!C30 -> Queen’s University | D58: Data analyst | E58: =Tuition_Data!D30 -> 59338 | F58: =Tuition_Data!G30 -> 87246 | G58: =SUMIFS(Salary_Data!$C$2:$C$13,Salary_Data!$A$2:$A$13,A58,Salary_Data!$B$2:$B$13,D58) -> 43056 | H58: =E58/G58 -> 1.3781587 | I58: =F58/G58 -> 2.0263378 | J58: =((5*G58-F58)/F58)*100 -> 146.75057 | K58: =((10*G58-F58)/F58)*100 -> 393.50113
A59: =Tuition_Data!A30 -> Canada | B59: =Tuition_Data!B30 -> Full-time Master of Management Analytics | C59: =Tuition_Data!C30 -> Queen’s University | D59: Data scientist | E59: =Tuition_Data!D30 -> 59338 | F59: =Tuition_Data!G30 -> 87246 | G59: =SUMIFS(Salary_Data!$C$2:$C$13,Salary_Data!$A$2:$A$13,A59,Salary_Data!$B$2:$B$13,D59) -> 50856 | H59: =E59/G59 -> 1.1667846 | I59: =F59/G59 -> 1.7155498 | J59: =((5*G59-F59)/F59)*100 -> 191.45176 | K59: =((10*G59-F59)/F59)*100 -> 482.90351
A60: =Tuition_Data!A31 -> Canada | B60: =Tuition_Data!B31 -> Master of Digital Transformation and Innovation — Applied Data Science | C60: =Tuition_Data!C31 -> University of Ottawa | D60: Data analyst | E60: =Tuition_Data!D31 -> 27859 | F60: =Tuition_Data!G31 -> 58217 | G60: =SUMIFS(Salary_Data!$C$2:$C$13,Salary_Data!$A$2:$A$13,A60,Salary_Data!$B$2:$B$13,D60) -> 43056 | H60: =E60/G60 -> 0.64704106 | I60: =F60/G60 -> 1.3521228 | J60: =((5*G60-F60)/F60)*100 -> 269.78889 | K60: =((10*G60-F60)/F60)*100 -> 639.57779
A61: =Tuition_Data!A31 -> Canada | B61: =Tuition_Data!B31 -> Master of Digital Transformation and Innovation — Applied Data Science | C61: =Tuition_Data!C31 -> University of Ottawa | D61: Data scientist | E61: =Tuition_Data!D31 -> 27859 | F61: =Tuition_Data!G31 -> 58217 | G61: =SUMIFS(Salary_Data!$C$2:$C$13,Salary_Data!$A$2:$A$13,A61,Salary_Data!$B$2:$B$13,D61) -> 50856 | H61: =E61/G61 -> 0.54780164 | I61: =F61/G61 -> 1.144742 | J61: =((5*G61-F61)/F61)*100 -> 336.77963 | K61: =((10*G61-F61)/F61)*100 -> 773.55927
A62: =Tuition_Data!A32 -> Australia | B62: =Tuition_Data!B32 -> Master of Data Science and Decisions | C62: =Tuition_Data!C32 -> UNSW Sydney | D62: Data analyst | E62: =Tuition_Data!D32 -> 88195 | F62: =Tuition_Data!G32 -> 144573 | G62: =SUMIFS(Salary_Data!$C$2:$C$13,Salary_Data!$A$2:$A$13,A62,Salary_Data!$B$2:$B$13,D62) -> 45435 | H62: =E62/G62 -> 1.9411247 | I62: =F62/G62 -> 3.1819742 | J62: =((5*G62-F62)/F62)*100 -> 57.13515 | K62: =((10*G62-F62)/F62)*100 -> 214.2703
A63: =Tuition_Data!A32 -> Australia | B63: =Tuition_Data!B32 -> Master of Data Science and Decisions | C63: =Tuition_Data!C32 -> UNSW Sydney | D63: Data scientist | E63: =Tuition_Data!D32 -> 88195 | F63: =Tuition_Data!G32 -> 144573 | G63: =SUMIFS(Salary_Data!$C$2:$C$13,Salary_Data!$A$2:$A$13,A63,Salary_Data!$B$2:$B$13,D63) -> 49280 | H63: =E63/G63 -> 1.7896713 | I63: =F63/G63 -> 2.9337054 | J63: =((5*G63-F63)/F63)*100 -> 70.43293 | K63: =((10*G63-F63)/F63)*100 -> 240.86586
A64: =Tuition_Data!A33 -> Australia | B64: =Tuition_Data!B33 -> Master of Data Science | C64: =Tuition_Data!C33 -> University of Melbourne | D64: Data analyst | E64: =Tuition_Data!D33 -> 85232 | F64: =Tuition_Data!G33 -> 142722 | G64: =SUMIFS(Salary_Data!$C$2:$C$13,Salary_Data!$A$2:$A$13,A64,Salary_Data!$B$2:$B$13,D64) -> 45435 | H64: =E64/G64 -> 1.8759106 | I64: =F64/G64 -> 3.1412347 | J64: =((5*G64-F64)/F64)*100 -> 59.173078 | K64: =((10*G64-F64)/F64)*100 -> 218.34616
A65: =Tuition_Data!A33 -> Australia | B65: =Tuition_Data!B33 -> Master of Data Science | C65: =Tuition_Data!C33 -> University of Melbourne | D65: Data scientist | E65: =Tuition_Data!D33 -> 85232 | F65: =Tuition_Data!G33 -> 142722 | G65: =SUMIFS(Salary_Data!$C$2:$C$13,Salary_Data!$A$2:$A$13,A65,Salary_Data!$B$2:$B$13,D65) -> 49280 | H65: =E65/G65 -> 1.7295455 | I65: =F65/G65 -> 2.8961445 | J65: =((5*G65-F65)/F65)*100 -> 72.643321 | K65: =((10*G65-F65)/F65)*100 -> 245.28664
A66: =Tuition_Data!A34 -> Australia | B66: =Tuition_Data!B34 -> Master of Data Science | C66: =Tuition_Data!C34 -> University of Sydney | D66: Data analyst | E66: =Tuition_Data!D34 -> 63836 | F66: =Tuition_Data!G34 -> 121327 | G66: =SUMIFS(Salary_Data!$C$2:$C$13,Salary_Data!$A$2:$A$13,A66,Salary_Data!$B$2:$B$13,D66) -> 45435 | H66: =E66/G66 -> 1.4049961 | I66: =F66/G66 -> 2.6703422 | J66: =((5*G66-F66)/F66)*100 -> 87.241916 | K66: =((10*G66-F66)/F66)*100 -> 274.48383
A67: =Tuition_Data!A34 -> Australia | B67: =Tuition_Data!B34 -> Master of Data Science | C67: =Tuition_Data!C34 -> University of Sydney | D67: Data scientist | E67: =Tuition_Data!D34 -> 63836 | F67: =Tuition_Data!G34 -> 121327 | G67: =SUMIFS(Salary_Data!$C$2:$C$13,Salary_Data!$A$2:$A$13,A67,Salary_Data!$B$2:$B$13,D67) -> 49280 | H67: =E67/G67 -> 1.2953734 | I67: =F67/G67 -> 2.4619927 | J67: =((5*G67-F67)/F67)*100 -> 103.08752 | K67: =((10*G67-F67)/F67)*100 -> 306.17505
A68: =Tuition_Data!A35 -> Australia | B68: =Tuition_Data!B35 -> Master of Statistics | C68: =Tuition_Data!C35 -> Australian National University | D68: Data analyst | E68: =Tuition_Data!D35 -> 78563 | F68: =Tuition_Data!G35 -> 130454 | G68: =SUMIFS(Salary_Data!$C$2:$C$13,Salary_Data!$A$2:$A$13,A68,Salary_Data!$B$2:$B$13,D68) -> 45435 | H68: =E68/G68 -> 1.7291295 | I68: =F68/G68 -> 2.8712226 | J68: =((5*G68-F68)/F68)*100 -> 74.141843 | K68: =((10*G68-F68)/F68)*100 -> 248.28369
A69: =Tuition_Data!A35 -> Australia | B69: =Tuition_Data!B35 -> Master of Statistics | C69: =Tuition_Data!C35 -> Australian National University | D69: Data scientist | E69: =Tuition_Data!D35 -> 78563 | F69: =Tuition_Data!G35 -> 130454 | G69: =SUMIFS(Salary_Data!$C$2:$C$13,Salary_Data!$A$2:$A$13,A69,Salary_Data!$B$2:$B$13,D69) -> 49280 | H69: =E69/G69 -> 1.5942167 | I69: =F69/G69 -> 2.6471997 | J69: =((5*G69-F69)/F69)*100 -> 88.878839 | K69: =((10*G69-F69)/F69)*100 -> 277.75768
A70: =Tuition_Data!A36 -> Australia | B70: =Tuition_Data!B36 -> Master of Data Science | C70: =Tuition_Data!C36 -> Monash University | D70: Data analyst | E70: =Tuition_Data!D36 -> 77975 | F70: =Tuition_Data!G36 -> 131966 | G70: =SUMIFS(Salary_Data!$C$2:$C$13,Salary_Data!$A$2:$A$13,A70,Salary_Data!$B$2:$B$13,D70) -> 45435 | H70: =E70/G70 -> 1.716188 | I70: =F70/G70 -> 2.9045009 | J70: =((5*G70-F70)/F70)*100 -> 72.146614 | K70: =((10*G70-F70)/F70)*100 -> 244.29323
A71: =Tuition_Data!A36 -> Australia | B71: =Tuition_Data!B36 -> Master of Data Science | C71: =Tuition_Data!C36 -> Monash University | D71: Data scientist | E71: =Tuition_Data!D36 -> 77975 | F71: =Tuition_Data!G36 -> 131966 | G71: =SUMIFS(Salary_Data!$C$2:$C$13,Salary_Data!$A$2:$A$13,A71,Salary_Data!$B$2:$B$13,D71) -> 49280 | H71: =E71/G71 -> 1.5822849 | I71: =F71/G71 -> 2.6778815 | J71: =((5*G71-F71)/F71)*100 -> 86.71476 | K71: =((10*G71-F71)/F71)*100 -> 273.42952
A72: =Tuition_Data!A37 -> Australia | B72: =Tuition_Data!B37 -> Master of Data Science | C72: =Tuition_Data!C37 -> University of Queensland | D72: Data analyst | E72: =Tuition_Data!D37 -> 85328 | F72: =Tuition_Data!G37 -> 129691 | G72: =SUMIFS(Salary_Data!$C$2:$C$13,Salary_Data!$A$2:$A$13,A72,Salary_Data!$B$2:$B$13,D72) -> 45435 | H72: =E72/G72 -> 1.8780236 | I72: =F72/G72 -> 2.8544294 | J72: =((5*G72-F72)/F72)*100 -> 75.166357 | K72: =((10*G72-F72)/F72)*100 -> 250.33271
A73: =Tuition_Data!A37 -> Australia | B73: =Tuition_Data!B37 -> Master of Data Science | C73: =Tuition_Data!C37 -> University of Queensland | D73: Data scientist | E73: =Tuition_Data!D37 -> 85328 | F73: =Tuition_Data!G37 -> 129691 | G73: =SUMIFS(Salary_Data!$C$2:$C$13,Salary_Data!$A$2:$A$13,A73,Salary_Data!$B$2:$B$13,D73) -> 49280 | H73: =E73/G73 -> 1.7314935 | I73: =F73/G73 -> 2.6317167 | J73: =((5*G73-F73)/F73)*100 -> 89.990053 | K73: =((10*G73-F73)/F73)*100 -> 279.98011
A74: =Tuition_Data!A38 -> Australia | B74: =Tuition_Data!B38 -> Master of Data Science | C74: =Tuition_Data!C38 -> University of Western Australia | D74: Data analyst | E74: =Tuition_Data!D38 -> 64956 | F74: =Tuition_Data!G38 -> 137425 | G74: =SUMIFS(Salary_Data!$C$2:$C$13,Salary_Data!$A$2:$A$13,A74,Salary_Data!$B$2:$B$13,D74) -> 45435 | H74: =E74/G74 -> 1.4296467 | I74: =F74/G74 -> 3.0246506 | J74: =((5*G74-F74)/F74)*100 -> 65.30835 | K74: =((10*G74-F74)/F74)*100 -> 230.6167
A75: =Tuition_Data!A38 -> Australia | B75: =Tuition_Data!B38 -> Master of Data Science | C75: =Tuition_Data!C38 -> University of Western Australia | D75: Data scientist | E75: =Tuition_Data!D38 -> 64956 | F75: =Tuition_Data!G38 -> 137425 | G75: =SUMIFS(Salary_Data!$C$2:$C$13,Salary_Data!$A$2:$A$13,A75,Salary_Data!$B$2:$B$13,D75) -> 49280 | H75: =E75/G75 -> 1.3181006 | I75: =F75/G75 -> 2.7886567 | J75: =((5*G75-F75)/F75)*100 -> 79.297799 | K75: =((10*G75-F75)/F75)*100 -> 258.5956
A76: =Tuition_Data!A39 -> Australia | B76: =Tuition_Data!B39 -> Master of Data Science | C76: =Tuition_Data!C39 -> Adelaide University | D76: Data analyst | E76: =Tuition_Data!D39 -> 76855 | F76: =Tuition_Data!G39 -> 116567 | G76: =SUMIFS(Salary_Data!$C$2:$C$13,Salary_Data!$A$2:$A$13,A76,Salary_Data!$B$2:$B$13,D76) -> 45435 | H76: =E76/G76 -> 1.6915374 | I76: =F76/G76 -> 2.5655772 | J76: =((5*G76-F76)/F76)*100 -> 94.887919 | K76: =((10*G76-F76)/F76)*100 -> 289.77584
A77: =Tuition_Data!A39 -> Australia | B77: =Tuition_Data!B39 -> Master of Data Science | C77: =Tuition_Data!C39 -> Adelaide University | D77: Data scientist | E77: =Tuition_Data!D39 -> 76855 | F77: =Tuition_Data!G39 -> 116567 | G77: =SUMIFS(Salary_Data!$C$2:$C$13,Salary_Data!$A$2:$A$13,A77,Salary_Data!$B$2:$B$13,D77) -> 49280 | H77: =E77/G77 -> 1.5595576 | I77: =F77/G77 -> 2.3654018 | J77: =((5*G77-F77)/F77)*100 -> 111.38058 | K77: =((10*G77-F77)/F77)*100 -> 322.76116
A78: =Tuition_Data!A40 -> Australia | B78: =Tuition_Data!B40 -> Master of Data Science and Innovation | C78: =Tuition_Data!C40 -> University of Technology Sydney | D78: Data analyst | E78: =Tuition_Data!D40 -> 70648 | F78: =Tuition_Data!G40 -> 118862 | G78: =SUMIFS(Salary_Data!$C$2:$C$13,Salary_Data!$A$2:$A$13,A78,Salary_Data!$B$2:$B$13,D78) -> 45435 | H78: =E78/G78 -> 1.5549246 | I78: =F78/G78 -> 2.6160889 | J78: =((5*G78-F78)/F78)*100 -> 91.125002 | K78: =((10*G78-F78)/F78)*100 -> 282.25
A79: =Tuition_Data!A40 -> Australia | B79: =Tuition_Data!B40 -> Master of Data Science and Innovation | C79: =Tuition_Data!C40 -> University of Technology Sydney | D79: Data scientist | E79: =Tuition_Data!D40 -> 70648 | F79: =Tuition_Data!G40 -> 118862 | G79: =SUMIFS(Salary_Data!$C$2:$C$13,Salary_Data!$A$2:$A$13,A79,Salary_Data!$B$2:$B$13,D79) -> 49280 | H79: =E79/G79 -> 1.4336039 | I79: =F79/G79 -> 2.4119724 | J79: =((5*G79-F79)/F79)*100 -> 107.29922 | K79: =((10*G79-F79)/F79)*100 -> 314.59844
A80: =Tuition_Data!A41 -> Australia | B80: =Tuition_Data!B41 -> Master of Data Science | C80: =Tuition_Data!C41 -> RMIT University | D80: Data analyst | E80: =Tuition_Data!D41 -> 65852 | F80: =Tuition_Data!G41 -> 119355 | G80: =SUMIFS(Salary_Data!$C$2:$C$13,Salary_Data!$A$2:$A$13,A80,Salary_Data!$B$2:$B$13,D80) -> 45435 | H80: =E80/G80 -> 1.4493672 | I80: =F80/G80 -> 2.6269396 | J80: =((5*G80-F80)/F80)*100 -> 90.335554 | K80: =((10*G80-F80)/F80)*100 -> 280.67111
A81: =Tuition_Data!A41 -> Australia | B81: =Tuition_Data!B41 -> Master of Data Science | C81: =Tuition_Data!C41 -> RMIT University | D81: Data scientist | E81: =Tuition_Data!D41 -> 65852 | F81: =Tuition_Data!G41 -> 119355 | G81: =SUMIFS(Salary_Data!$C$2:$C$13,Salary_Data!$A$2:$A$13,A81,Salary_Data!$B$2:$B$13,D81) -> 49280 | H81: =E81/G81 -> 1.3362825 | I81: =F81/G81 -> 2.4219765 | J81: =((5*G81-F81)/F81)*100 -> 106.44296 | K81: =((10*G81-F81)/F81)*100 -> 312.88593
A82: =Tuition_Data!A42 -> Germany | B82: =Tuition_Data!B42 -> M.Sc. Data Engineering and Analytics | C82: =Tuition_Data!C42 -> Technical University of Munich | D82: Data analyst | E82: =Tuition_Data!D42 -> 27334 | F82: =Tuition_Data!G42 -> 62867 | G82: =SUMIFS(Salary_Data!$C$2:$C$13,Salary_Data!$A$2:$A$13,A82,Salary_Data!$B$2:$B$13,D82) -> 41467 | H82: =E82/G82 -> 0.65917477 | I82: =F82/G82 -> 1.516073 | J82: =((5*G82-F82)/F82)*100 -> 229.79942 | K82: =((10*G82-F82)/F82)*100 -> 559.59884
A83: =Tuition_Data!A42 -> Germany | B83: =Tuition_Data!B42 -> M.Sc. Data Engineering and Analytics | C83: =Tuition_Data!C42 -> Technical University of Munich | D83: Data scientist | E83: =Tuition_Data!D42 -> 27334 | F83: =Tuition_Data!G42 -> 62867 | G83: =SUMIFS(Salary_Data!$C$2:$C$13,Salary_Data!$A$2:$A$13,A83,Salary_Data!$B$2:$B$13,D83) -> 46310 | H83: =E83/G83 -> 0.59023969 | I83: =F83/G83 -> 1.3575254 | J83: =((5*G83-F83)/F83)*100 -> 268.31724 | K83: =((10*G83-F83)/F83)*100 -> 636.63448
A84: =Tuition_Data!A43 -> Germany | B84: =Tuition_Data!B43 -> M.Sc. Statistics and Data Science | C84: =Tuition_Data!C43 -> LMU Munich | D84: Data analyst | E84: =Tuition_Data!D43 -> 0 | F84: =Tuition_Data!G43 -> 41000 | G84: =SUMIFS(Salary_Data!$C$2:$C$13,Salary_Data!$A$2:$A$13,A84,Salary_Data!$B$2:$B$13,D84) -> 41467 | H84: =E84/G84 -> 0 | I84: =F84/G84 -> 0.98873803 | J84: =((5*G84-F84)/F84)*100 -> 405.69512 | K84: =((10*G84-F84)/F84)*100 -> 911.39024
A85: =Tuition_Data!A43 -> Germany | B85: =Tuition_Data!B43 -> M.Sc. Statistics and Data Science | C85: =Tuition_Data!C43 -> LMU Munich | D85: Data scientist | E85: =Tuition_Data!D43 -> 0 | F85: =Tuition_Data!G43 -> 41000 | G85: =SUMIFS(Salary_Data!$C$2:$C$13,Salary_Data!$A$2:$A$13,A85,Salary_Data!$B$2:$B$13,D85) -> 46310 | H85: =E85/G85 -> 0 | I85: =F85/G85 -> 0.88533794 | J85: =((5*G85-F85)/F85)*100 -> 464.7561 | K85: =((10*G85-F85)/F85)*100 -> 1029.5122
A86: =Tuition_Data!A44 -> Germany | B86: =Tuition_Data!B44 -> M.Sc. Data and Computer Science | C86: =Tuition_Data!C44 -> Heidelberg University | D86: Data analyst | E86: =Tuition_Data!D44 -> 6833 | F86: =Tuition_Data!G44 -> 34167 | G86: =SUMIFS(Salary_Data!$C$2:$C$13,Salary_Data!$A$2:$A$13,A86,Salary_Data!$B$2:$B$13,D86) -> 41467 | H86: =E86/G86 -> 0.16478163 | I86: =F86/G86 -> 0.8239564 | J86: =((5*G86-F86)/F86)*100 -> 506.82823 | K86: =((10*G86-F86)/F86)*100 -> 1113.6565
A87: =Tuition_Data!A44 -> Germany | B87: =Tuition_Data!B44 -> M.Sc. Data and Computer Science | C87: =Tuition_Data!C44 -> Heidelberg University | D87: Data scientist | E87: =Tuition_Data!D44 -> 6833 | F87: =Tuition_Data!G44 -> 34167 | G87: =SUMIFS(Salary_Data!$C$2:$C$13,Salary_Data!$A$2:$A$13,A87,Salary_Data!$B$2:$B$13,D87) -> 46310 | H87: =E87/G87 -> 0.14754913 | I87: =F87/G87 -> 0.73778881 | J87: =((5*G87-F87)/F87)*100 -> 577.70071 | K87: =((10*G87-F87)/F87)*100 -> 1255.4014
A88: =Tuition_Data!A45 -> Germany | B88: =Tuition_Data!B45 -> M.Sc. Data Science | C88: =Tuition_Data!C45 -> Freie Universität Berlin | D88: Data analyst | E88: =Tuition_Data!D45 -> 0 | F88: =Tuition_Data!G45 -> 27115 | G88: =SUMIFS(Salary_Data!$C$2:$C$13,Salary_Data!$A$2:$A$13,A88,Salary_Data!$B$2:$B$13,D88) -> 41467 | H88: =E88/G88 -> 0 | I88: =F88/G88 -> 0.65389346 | J88: =((5*G88-F88)/F88)*100 -> 664.65056 | K88: =((10*G88-F88)/F88)*100 -> 1429.3011
A89: =Tuition_Data!A45 -> Germany | B89: =Tuition_Data!B45 -> M.Sc. Data Science | C89: =Tuition_Data!C45 -> Freie Universität Berlin | D89: Data scientist | E89: =Tuition_Data!D45 -> 0 | F89: =Tuition_Data!G45 -> 27115 | G89: =SUMIFS(Salary_Data!$C$2:$C$13,Salary_Data!$A$2:$A$13,A89,Salary_Data!$B$2:$B$13,D89) -> 46310 | H89: =E89/G89 -> 0 | I89: =F89/G89 -> 0.58551069 | J89: =((5*G89-F89)/F89)*100 -> 753.95538 | K89: =((10*G89-F89)/F89)*100 -> 1607.9108
A90: =Tuition_Data!A46 -> Germany | B90: =Tuition_Data!B46 -> M.Sc. Data Science | C90: =Tuition_Data!C46 -> RWTH Aachen University | D90: Data analyst | E90: =Tuition_Data!D46 -> 0 | F90: =Tuition_Data!G46 -> 30067 | G90: =SUMIFS(Salary_Data!$C$2:$C$13,Salary_Data!$A$2:$A$13,A90,Salary_Data!$B$2:$B$13,D90) -> 41467 | H90: =E90/G90 -> 0 | I90: =F90/G90 -> 0.7250826 | J90: =((5*G90-F90)/F90)*100 -> 589.57661 | K90: =((10*G90-F90)/F90)*100 -> 1279.1532
A91: =Tuition_Data!A46 -> Germany | B91: =Tuition_Data!B46 -> M.Sc. Data Science | C91: =Tuition_Data!C46 -> RWTH Aachen University | D91: Data scientist | E91: =Tuition_Data!D46 -> 0 | F91: =Tuition_Data!G46 -> 30067 | G91: =SUMIFS(Salary_Data!$C$2:$C$13,Salary_Data!$A$2:$A$13,A91,Salary_Data!$B$2:$B$13,D91) -> 46310 | H91: =E91/G91 -> 0 | I91: =F91/G91 -> 0.64925502 | J91: =((5*G91-F91)/F91)*100 -> 670.11341 | K91: =((10*G91-F91)/F91)*100 -> 1440.2268
A92: =Tuition_Data!A47 -> Germany | B92: =Tuition_Data!B47 -> M.Sc. Computational and Data Science | C92: =Tuition_Data!C47 -> Karlsruhe Institute of Technology | D92: Data analyst | E92: =Tuition_Data!D47 -> 6833 | F92: =Tuition_Data!G47 -> 30067 | G92: =SUMIFS(Salary_Data!$C$2:$C$13,Salary_Data!$A$2:$A$13,A92,Salary_Data!$B$2:$B$13,D92) -> 41467 | H92: =E92/G92 -> 0.16478163 | I92: =F92/G92 -> 0.7250826 | J92: =((5*G92-F92)/F92)*100 -> 589.57661 | K92: =((10*G92-F92)/F92)*100 -> 1279.1532
A93: =Tuition_Data!A47 -> Germany | B93: =Tuition_Data!B47 -> M.Sc. Computational and Data Science | C93: =Tuition_Data!C47 -> Karlsruhe Institute of Technology | D93: Data scientist | E93: =Tuition_Data!D47 -> 6833 | F93: =Tuition_Data!G47 -> 30067 | G93: =SUMIFS(Salary_Data!$C$2:$C$13,Salary_Data!$A$2:$A$13,A93,Salary_Data!$B$2:$B$13,D93) -> 46310 | H93: =E93/G93 -> 0.14754913 | I93: =F93/G93 -> 0.64925502 | J93: =((5*G93-F93)/F93)*100 -> 670.11341 | K93: =((10*G93-F93)/F93)*100 -> 1440.2268
A94: =Tuition_Data!A48 -> Germany | B94: =Tuition_Data!B48 -> M.Sc. Statistics | C94: =Tuition_Data!C48 -> Humboldt-Universität zu Berlin / BUA joint degree | D94: Data analyst | E94: =Tuition_Data!D48 -> 0 | F94: =Tuition_Data!G48 -> 27115 | G94: =SUMIFS(Salary_Data!$C$2:$C$13,Salary_Data!$A$2:$A$13,A94,Salary_Data!$B$2:$B$13,D94) -> 41467 | H94: =E94/G94 -> 0 | I94: =F94/G94 -> 0.65389346 | J94: =((5*G94-F94)/F94)*100 -> 664.65056 | K94: =((10*G94-F94)/F94)*100 -> 1429.3011
A95: =Tuition_Data!A48 -> Germany | B95: =Tuition_Data!B48 -> M.Sc. Statistics | C95: =Tuition_Data!C48 -> Humboldt-Universität zu Berlin / BUA joint degree | D95: Data scientist | E95: =Tuition_Data!D48 -> 0 | F95: =Tuition_Data!G48 -> 27115 | G95: =SUMIFS(Salary_Data!$C$2:$C$13,Salary_Data!$A$2:$A$13,A95,Salary_Data!$B$2:$B$13,D95) -> 46310 | H95: =E95/G95 -> 0 | I95: =F95/G95 -> 0.58551069 | J95: =((5*G95-F95)/F95)*100 -> 753.95538 | K95: =((10*G95-F95)/F95)*100 -> 1607.9108
A96: =Tuition_Data!A49 -> Germany | B96: =Tuition_Data!B49 -> M.Sc. Computational Modeling and Simulation | C96: =Tuition_Data!C49 -> TU Dresden | D96: Data analyst | E96: =Tuition_Data!D49 -> 0 | F96: =Tuition_Data!G49 -> 28700 | G96: =SUMIFS(Salary_Data!$C$2:$C$13,Salary_Data!$A$2:$A$13,A96,Salary_Data!$B$2:$B$13,D96) -> 41467 | H96: =E96/G96 -> 0 | I96: =F96/G96 -> 0.69211662 | J96: =((5*G96-F96)/F96)*100 -> 622.4216 | K96: =((10*G96-F96)/F96)*100 -> 1344.8432
A97: =Tuition_Data!A49 -> Germany | B97: =Tuition_Data!B49 -> M.Sc. Computational Modeling and Simulation | C97: =Tuition_Data!C49 -> TU Dresden | D97: Data scientist | E97: =Tuition_Data!D49 -> 0 | F97: =Tuition_Data!G49 -> 28700 | G97: =SUMIFS(Salary_Data!$C$2:$C$13,Salary_Data!$A$2:$A$13,A97,Salary_Data!$B$2:$B$13,D97) -> 46310 | H97: =E97/G97 -> 0 | I97: =F97/G97 -> 0.61973656 | J97: =((5*G97-F97)/F97)*100 -> 706.79443 | K97: =((10*G97-F97)/F97)*100 -> 1513.5889
A98: =Tuition_Data!A50 -> Germany | B98: =Tuition_Data!B50 -> M.Sc. Data Science and Artificial Intelligence | C98: =Tuition_Data!C50 -> University of Hamburg | D98: Data analyst | E98: =Tuition_Data!D50 -> 0 | F98: =Tuition_Data!G50 -> 35397 | G98: =SUMIFS(Salary_Data!$C$2:$C$13,Salary_Data!$A$2:$A$13,A98,Salary_Data!$B$2:$B$13,D98) -> 41467 | H98: =E98/G98 -> 0 | I98: =F98/G98 -> 0.85361854 | J98: =((5*G98-F98)/F98)*100 -> 485.74173 | K98: =((10*G98-F98)/F98)*100 -> 1071.4835
A99: =Tuition_Data!A50 -> Germany | B99: =Tuition_Data!B50 -> M.Sc. Data Science and Artificial Intelligence | C99: =Tuition_Data!C50 -> University of Hamburg | D99: Data scientist | E99: =Tuition_Data!D50 -> 0 | F99: =Tuition_Data!G50 -> 35397 | G99: =SUMIFS(Salary_Data!$C$2:$C$13,Salary_Data!$A$2:$A$13,A99,Salary_Data!$B$2:$B$13,D99) -> 46310 | H99: =E99/G99 -> 0 | I99: =F99/G99 -> 0.76434895 | J99: =((5*G99-F99)/F99)*100 -> 554.15148 | K99: =((10*G99-F99)/F99)*100 -> 1208.303
A100: =Tuition_Data!A51 -> Germany | B100: =Tuition_Data!B51 -> M.Sc. Data Science | C100: =Tuition_Data!C51 -> FAU Erlangen–Nürnberg | D100: Data analyst | E100: =Tuition_Data!D51 -> 0 | F100: =Tuition_Data!G51 -> 26514 | G100: =SUMIFS(Salary_Data!$C$2:$C$13,Salary_Data!$A$2:$A$13,A100,Salary_Data!$B$2:$B$13,D100) -> 41467 | H100: =E100/G100 -> 0 | I100: =F100/G100 -> 0.6394 | J100: =((5*G100-F100)/F100)*100 -> 681.9831 | K100: =((10*G100-F100)/F100)*100 -> 1463.9662
...

Sheet Summary
A1: Country | B1: Occupation | C1: Basic Payback - Median (yrs) | D1: Basic Payback - IQR Low (yrs) | E1: Basic Payback - IQR High (yrs) | F1: Realistic Payback - Median (yrs) | G1: Realistic Payback - IQR Low (yrs) | H1: Realistic Payback - IQR High (yrs) | I1: 5yr ROI - Median (%) | J1: 5yr ROI - IQR Low (%) | K1: 5yr ROI - IQR High (%) | L1: 10yr ROI - Median (%) | M1: 10yr ROI - IQR Low (%) | N1: 10yr ROI - IQR High (%)
A2: United States | B2: Data analyst | C2: {=MEDIAN(IF(((ROI_Calculations!$A$2:$A$121=A2)*(ROI_Calculations!$D$2:$D$121=B2)),ROI_Calculations!$H$2:$H$121))} -> 1.4404447 | D2: {=PERCENTILE(IF(((ROI_Calculations!$A$2:$A$121=A2)*(ROI_Calculations!$D$2:$D$121=B2)),ROI_Calculations!$H$2:$H$121),0.25)} -> 1.3165961 | E2: {=PERCENTILE(IF(((ROI_Calculations!$A$2:$A$121=A2)*(ROI_Calculations!$D$2:$D$121=B2)),ROI_Calculations!$H$2:$H$121),0.75)} -> 1.6715281 | F2: {=MEDIAN(IF(((ROI_Calculations!$A$2:$A$121=A2)*(ROI_Calculations!$D$2:$D$121=B2)),ROI_Calculations!$I$2:$I$121))} -> 2.5377537 | G2: {=PERCENTILE(IF(((ROI_Calculations!$A$2:$A$121=A2)*(ROI_Calculations!$D$2:$D$121=B2)),ROI_Calculations!$I$2:$I$121),0.25)} -> 2.2208047 | H2: {=PERCENTILE(IF(((ROI_Calculations!$A$2:$A$121=A2)*(ROI_Calculations!$D$2:$D$121=B2)),ROI_Calculations!$I$2:$I$121),0.75)} -> 2.6821158 | I2: {=MEDIAN(IF(((ROI_Calculations!$A$2:$A$121=A2)*(ROI_Calculations!$D$2:$D$121=B2)),ROI_Calculations!$J$2:$J$121))} -> 97.518267 | J2: {=PERCENTILE(IF(((ROI_Calculations!$A$2:$A$121=A2)*(ROI_Calculations!$D$2:$D$121=B2)),ROI_Calculations!$J$2:$J$121),0.25)} -> 86.420113 | K2: {=PERCENTILE(IF(((ROI_Calculations!$A$2:$A$121=A2)*(ROI_Calculations!$D$2:$D$121=B2)),ROI_Calculations!$J$2:$J$121),0.75)} -> 125.4982 | L2: {=MEDIAN(IF(((ROI_Calculations!$A$2:$A$121=A2)*(ROI_Calculations!$D$2:$D$121=B2)),ROI_Calculations!$K$2:$K$121))} -> 295.03653 | M2: {=PERCENTILE(IF(((ROI_Calculations!$A$2:$A$121=A2)*(ROI_Calculations!$D$2:$D$121=B2)),ROI_Calculations!$K$2:$K$121),0.25)} -> 272.84023 | N2: {=PERCENTILE(IF(((ROI_Calculations!$A$2:$A$121=A2)*(ROI_Calculations!$D$2:$D$121=B2)),ROI_Calculations!$K$2:$K$121),0.75)} -> 350.99639
A3: United States | B3: Data scientist | C3: {=MEDIAN(IF(((ROI_Calculations!$A$2:$A$121=A3)*(ROI_Calculations!$D$2:$D$121=B3)),ROI_Calculations!$H$2:$H$121))} -> 1.1867413 | D3: {=PERCENTILE(IF(((ROI_Calculations!$A$2:$A$121=A3)*(ROI_Calculations!$D$2:$D$121=B3)),ROI_Calculations!$H$2:$H$121),0.25)} -> 1.084706 | E3: {=PERCENTILE(IF(((ROI_Calculations!$A$2:$A$121=A3)*(ROI_Calculations!$D$2:$D$121=B3)),ROI_Calculations!$H$2:$H$121),0.75)} -> 1.3771244 | F3: {=MEDIAN(IF(((ROI_Calculations!$A$2:$A$121=A3)*(ROI_Calculations!$D$2:$D$121=B3)),ROI_Calculations!$I$2:$I$121))} -> 2.0907829 | G3: {=PERCENTILE(IF(((ROI_Calculations!$A$2:$A$121=A3)*(ROI_Calculations!$D$2:$D$121=B3)),ROI_Calculations!$I$2:$I$121),0.25)} -> 1.8296576 | H3: {=PERCENTILE(IF(((ROI_Calculations!$A$2:$A$121=A3)*(ROI_Calculations!$D$2:$D$121=B3)),ROI_Calculations!$I$2:$I$121),0.75)} -> 2.2097187 | I3: {=MEDIAN(IF(((ROI_Calculations!$A$2:$A$121=A3)*(ROI_Calculations!$D$2:$D$121=B3)),ROI_Calculations!$J$2:$J$121))} -> 139.74403 | J3: {=PERCENTILE(IF(((ROI_Calculations!$A$2:$A$121=A3)*(ROI_Calculations!$D$2:$D$121=B3)),ROI_Calculations!$J$2:$J$121),0.25)} -> 126.27329 | K3: {=PERCENTILE(IF(((ROI_Calculations!$A$2:$A$121=A3)*(ROI_Calculations!$D$2:$D$121=B3)),ROI_Calculations!$J$2:$J$121),0.75)} -> 173.70555 | L3: {=MEDIAN(IF(((ROI_Calculations!$A$2:$A$121=A3)*(ROI_Calculations!$D$2:$D$121=B3)),ROI_Calculations!$K$2:$K$121))} -> 379.48805 | M3: {=PERCENTILE(IF(((ROI_Calculations!$A$2:$A$121=A3)*(ROI_Calculations!$D$2:$D$121=B3)),ROI_Calculations!$K$2:$K$121),0.25)} -> 352.54658 | N3: {=PERCENTILE(IF(((ROI_Calculations!$A$2:$A$121=A3)*(ROI_Calculations!$D$2:$D$121=B3)),ROI_Calculations!$K$2:$K$121),0.75)} -> 447.41109
A4: United Kingdom | B4: Data analyst | C4: {=MEDIAN(IF(((ROI_Calculations!$A$2:$A$121=A4)*(ROI_Calculations!$D$2:$D$121=B4)),ROI_Calculations!$H$2:$H$121))} -> 1.6337361 | D4: {=PERCENTILE(IF(((ROI_Calculations!$A$2:$A$121=A4)*(ROI_Calculations!$D$2:$D$121=B4)),ROI_Calculations!$H$2:$H$121),0.25)} -> 1.5530163 | E4: {=PERCENTILE(IF(((ROI_Calculations!$A$2:$A$121=A4)*(ROI_Calculations!$D$2:$D$121=B4)),ROI_Calculations!$H$2:$H$121),0.75)} -> 1.6700566 | F4: {=MEDIAN(IF(((ROI_Calculations!$A$2:$A$121=A4)*(ROI_Calculations!$D$2:$D$121=B4)),ROI_Calculations!$I$2:$I$121))} -> 2.4526335 | G4: {=PERCENTILE(IF(((ROI_Calculations!$A$2:$A$121=A4)*(ROI_Calculations!$D$2:$D$121=B4)),ROI_Calculations!$I$2:$I$121),0.25)} -> 2.342842 | H4: {=PERCENTILE(IF(((ROI_Calculations!$A$2:$A$121=A4)*(ROI_Calculations!$D$2:$D$121=B4)),ROI_Calculations!$I$2:$I$121),0.75)} -> 2.5530548 | I4: {=MEDIAN(IF(((ROI_Calculations!$A$2:$A$121=A4)*(ROI_Calculations!$D$2:$D$121=B4)),ROI_Calculations!$J$2:$J$121))} -> 103.86696 | J4: {=PERCENTILE(IF(((ROI_Calculations!$A$2:$A$121=A4)*(ROI_Calculations!$D$2:$D$121=B4)),ROI_Calculations!$J$2:$J$121),0.25)} -> 95.845771 | K4: {=PERCENTILE(IF(((ROI_Calculations!$A$2:$A$121=A4)*(ROI_Calculations!$D$2:$D$121=B4)),ROI_Calculations!$J$2:$J$121),0.75)} -> 113.50587 | L4: {=MEDIAN(IF(((ROI_Calculations!$A$2:$A$121=A4)*(ROI_Calculations!$D$2:$D$121=B4)),ROI_Calculations!$K$2:$K$121))} -> 307.73391 | M4: {=PERCENTILE(IF(((ROI_Calculations!$A$2:$A$121=A4)*(ROI_Calculations!$D$2:$D$121=B4)),ROI_Calculations!$K$2:$K$121),0.25)} -> 291.69154 | N4: {=PERCENTILE(IF(((ROI_Calculations!$A$2:$A$121=A4)*(ROI_Calculations!$D$2:$D$121=B4)),ROI_Calculations!$K$2:$K$121),0.75)} -> 327.01174
A5: United Kingdom | B5: Data scientist | C5: {=MEDIAN(IF(((ROI_Calculations!$A$2:$A$121=A5)*(ROI_Calculations!$D$2:$D$121=B5)),ROI_Calculations!$H$2:$H$121))} -> 1.2007955 | D5: {=PERCENTILE(IF(((ROI_Calculations!$A$2:$A$121=A5)*(ROI_Calculations!$D$2:$D$121=B5)),ROI_Calculations!$H$2:$H$121),0.25)} -> 1.1414665 | E5: {=PERCENTILE(IF(((ROI_Calculations!$A$2:$A$121=A5)*(ROI_Calculations!$D$2:$D$121=B5)),ROI_Calculations!$H$2:$H$121),0.75)} -> 1.227491 | F5: {=MEDIAN(IF(((ROI_Calculations!$A$2:$A$121=A5)*(ROI_Calculations!$D$2:$D$121=B5)),ROI_Calculations!$I$2:$I$121))} -> 1.8026848 | G5: {=PERCENTILE(IF(((ROI_Calculations!$A$2:$A$121=A5)*(ROI_Calculations!$D$2:$D$121=B5)),ROI_Calculations!$I$2:$I$121),0.25)} -> 1.7219881 | H5: {=PERCENTILE(IF(((ROI_Calculations!$A$2:$A$121=A5)*(ROI_Calculations!$D$2:$D$121=B5)),ROI_Calculations!$I$2:$I$121),0.75)} -> 1.8764944 | I5: {=MEDIAN(IF(((ROI_Calculations!$A$2:$A$121=A5)*(ROI_Calculations!$D$2:$D$121=B5)),ROI_Calculations!$J$2:$J$121))} -> 177.37014 | J5: {=PERCENTILE(IF(((ROI_Calculations!$A$2:$A$121=A5)*(ROI_Calculations!$D$2:$D$121=B5)),ROI_Calculations!$J$2:$J$121),0.25)} -> 166.45695 | K5: {=PERCENTILE(IF(((ROI_Calculations!$A$2:$A$121=A5)*(ROI_Calculations!$D$2:$D$121=B5)),ROI_Calculations!$J$2:$J$121),0.75)} -> 190.48431 | L5: {=MEDIAN(IF(((ROI_Calculations!$A$2:$A$121=A5)*(ROI_Calculations!$D$2:$D$121=B5)),ROI_Calculations!$K$2:$K$121))} -> 454.74028 | M5: {=PERCENTILE(IF(((ROI_Calculations!$A$2:$A$121=A5)*(ROI_Calculations!$D$2:$D$121=B5)),ROI_Calculations!$K$2:$K$121),0.25)} -> 432.91391 | N5: {=PERCENTILE(IF(((ROI_Calculations!$A$2:$A$121=A5)*(ROI_Calculations!$D$2:$D$121=B5)),ROI_Calculations!$K$2:$K$121),0.75)} -> 480.96863
A6: Canada | B6: Data analyst | C6: {=MEDIAN(IF(((ROI_Calculations!$A$2:$A$121=A6)*(ROI_Calculations!$D$2:$D$121=B6)),ROI_Calculations!$H$2:$H$121))} -> 0.99723616 | D6: {=PERCENTILE(IF(((ROI_Calculations!$A$2:$A$121=A6)*(ROI_Calculations!$D$2:$D$121=B6)),ROI_Calculations!$H$2:$H$121),0.25)} -> 0.94395671 | E6: {=PERCENTILE(IF(((ROI_Calculations!$A$2:$A$121=A6)*(ROI_Calculations!$D$2:$D$121=B6)),ROI_Calculations!$H$2:$H$121),0.75)} -> 1.282539 | F6: {=MEDIAN(IF(((ROI_Calculations!$A$2:$A$121=A6)*(ROI_Calculations!$D$2:$D$121=B6)),ROI_Calculations!$I$2:$I$121))} -> 1.613875 | G6: {=PERCENTILE(IF(((ROI_Calculations!$A$2:$A$121=A6)*(ROI_Calculations!$D$2:$D$121=B6)),ROI_Calculations!$I$2:$I$121),0.25)} -> 1.4392477 | H6: {=PERCENTILE(IF(((ROI_Calculations!$A$2:$A$121=A6)*(ROI_Calculations!$D$2:$D$121=B6)),ROI_Calculations!$I$2:$I$121),0.75)} -> 1.7372782 | I6: {=MEDIAN(IF(((ROI_Calculations!$A$2:$A$121=A6)*(ROI_Calculations!$D$2:$D$121=B6)),ROI_Calculations!$J$2:$J$121))} -> 209.96639 | J6: {=PERCENTILE(IF(((ROI_Calculations!$A$2:$A$121=A6)*(ROI_Calculations!$D$2:$D$121=B6)),ROI_Calculations!$J$2:$J$121),0.25)} -> 187.8493 | K6: {=PERCENTILE(IF(((ROI_Calculations!$A$2:$A$121=A6)*(ROI_Calculations!$D$2:$D$121=B6)),ROI_Calculations!$J$2:$J$121),0.75)} -> 247.58862 | L6: {=MEDIAN(IF(((ROI_Calculations!$A$2:$A$121=A6)*(ROI_Calculations!$D$2:$D$121=B6)),ROI_Calculations!$K$2:$K$121))} -> 519.93277 | M6: {=PERCENTILE(IF(((ROI_Calculations!$A$2:$A$121=A6)*(ROI_Calculations!$D$2:$D$121=B6)),ROI_Calculations!$K$2:$K$121),0.25)} -> 475.6986 | N6: {=PERCENTILE(IF(((ROI_Calculations!$A$2:$A$121=A6)*(ROI_Calculations!$D$2:$D$121=B6)),ROI_Calculations!$K$2:$K$121),0.75)} -> 595.17724
A7: Canada | B7: Data scientist | C7: {=MEDIAN(IF(((ROI_Calculations!$A$2:$A$121=A7)*(ROI_Calculations!$D$2:$D$121=B7)),ROI_Calculations!$H$2:$H$121))} -> 0.84428583 | D7: {=PERCENTILE(IF(((ROI_Calculations!$A$2:$A$121=A7)*(ROI_Calculations!$D$2:$D$121=B7)),ROI_Calculations!$H$2:$H$121),0.25)} -> 0.79917807 | E7: {=PERCENTILE(IF(((ROI_Calculations!$A$2:$A$121=A7)*(ROI_Calculations!$D$2:$D$121=B7)),ROI_Calculations!$H$2:$H$121),0.75)} -> 1.0858306 | F7: {=MEDIAN(IF(((ROI_Calculations!$A$2:$A$121=A7)*(ROI_Calculations!$D$2:$D$121=B7)),ROI_Calculations!$I$2:$I$121))} -> 1.3663481 | G7: {=PERCENTILE(IF(((ROI_Calculations!$A$2:$A$121=A7)*(ROI_Calculations!$D$2:$D$121=B7)),ROI_Calculations!$I$2:$I$121),0.25)} -> 1.2185042 | H7: {=PERCENTILE(IF(((ROI_Calculations!$A$2:$A$121=A7)*(ROI_Calculations!$D$2:$D$121=B7)),ROI_Calculations!$I$2:$I$121),0.75)} -> 1.4708245 | I7: {=MEDIAN(IF(((ROI_Calculations!$A$2:$A$121=A7)*(ROI_Calculations!$D$2:$D$121=B7)),ROI_Calculations!$J$2:$J$121))} -> 266.11972 | J7: {=PERCENTILE(IF(((ROI_Calculations!$A$2:$A$121=A7)*(ROI_Calculations!$D$2:$D$121=B7)),ROI_Calculations!$J$2:$J$121),0.25)} -> 239.99591 | K7: {=PERCENTILE(IF(((ROI_Calculations!$A$2:$A$121=A7)*(ROI_Calculations!$D$2:$D$121=B7)),ROI_Calculations!$J$2:$J$121),0.75)} -> 310.55757 | L7: {=MEDIAN(IF(((ROI_Calculations!$A$2:$A$121=A7)*(ROI_Calculations!$D$2:$D$121=B7)),ROI_Calculations!$K$2:$K$121))} -> 632.23943 | M7: {=PERCENTILE(IF(((ROI_Calculations!$A$2:$A$121=A7)*(ROI_Calculations!$D$2:$D$121=B7)),ROI_Calculations!$K$2:$K$121),0.25)} -> 579.99182 | N7: {=PERCENTILE(IF(((ROI_Calculations!$A$2:$A$121=A7)*(ROI_Calculations!$D$2:$D$121=B7)),ROI_Calculations!$K$2:$K$121),0.75)} -> 721.11514
A8: Australia | B8: Data analyst | C8: {=MEDIAN(IF(((ROI_Calculations!$A$2:$A$121=A8)*(ROI_Calculations!$D$2:$D$121=B8)),ROI_Calculations!$H$2:$H$121))} -> 1.7038627 | D8: {=PERCENTILE(IF(((ROI_Calculations!$A$2:$A$121=A8)*(ROI_Calculations!$D$2:$D$121=B8)),ROI_Calculations!$H$2:$H$121),0.25)} -> 1.4757566 | E8: {=PERCENTILE(IF(((ROI_Calculations!$A$2:$A$121=A8)*(ROI_Calculations!$D$2:$D$121=B8)),ROI_Calculations!$H$2:$H$121),0.75)} -> 1.8392154 | F8: {=MEDIAN(IF(((ROI_Calculations!$A$2:$A$121=A8)*(ROI_Calculations!$D$2:$D$121=B8)),ROI_Calculations!$I$2:$I$121))} -> 2.862826 | G8: {=PERCENTILE(IF(((ROI_Calculations!$A$2:$A$121=A8)*(ROI_Calculations!$D$2:$D$121=B8)),ROI_Calculations!$I$2:$I$121),0.25)} -> 2.6377902 | H8: {=PERCENTILE(IF(((ROI_Calculations!$A$2:$A$121=A8)*(ROI_Calculations!$D$2:$D$121=B8)),ROI_Calculations!$I$2:$I$121),0.75)} -> 2.9946132 | I8: {=MEDIAN(IF(((ROI_Calculations!$A$2:$A$121=A8)*(ROI_Calculations!$D$2:$D$121=B8)),ROI_Calculations!$J$2:$J$121))} -> 74.6541 | J8: {=PERCENTILE(IF(((ROI_Calculations!$A$2:$A$121=A8)*(ROI_Calculations!$D$2:$D$121=B8)),ROI_Calculations!$J$2:$J$121),0.25)} -> 67.017916 | K8: {=PERCENTILE(IF(((ROI_Calculations!$A$2:$A$121=A8)*(ROI_Calculations!$D$2:$D$121=B8)),ROI_Calculations!$J$2:$J$121),0.75)} -> 89.562144 | L8: {=MEDIAN(IF(((ROI_Calculations!$A$2:$A$121=A8)*(ROI_Calculations!$D$2:$D$121=B8)),ROI_Calculations!$K$2:$K$121))} -> 249.3082 | M8: {=PERCENTILE(IF(((ROI_Calculations!$A$2:$A$121=A8)*(ROI_Calculations!$D$2:$D$121=B8)),ROI_Calculations!$K$2:$K$121),0.25)} -> 234.03583 | N8: {=PERCENTILE(IF(((ROI_Calculations!$A$2:$A$121=A8)*(ROI_Calculations!$D$2:$D$121=B8)),ROI_Calculations!$K$2:$K$121),0.75)} -> 279.12429
A9: Australia | B9: Data scientist | C9: {=MEDIAN(IF(((ROI_Calculations!$A$2:$A$121=A9)*(ROI_Calculations!$D$2:$D$121=B9)),ROI_Calculations!$H$2:$H$121))} -> 1.5709213 | D9: {=PERCENTILE(IF(((ROI_Calculations!$A$2:$A$121=A9)*(ROI_Calculations!$D$2:$D$121=B9)),ROI_Calculations!$H$2:$H$121),0.25)} -> 1.3606128 | E9: {=PERCENTILE(IF(((ROI_Calculations!$A$2:$A$121=A9)*(ROI_Calculations!$D$2:$D$121=B9)),ROI_Calculations!$H$2:$H$121),0.75)} -> 1.6957133 | F9: {=MEDIAN(IF(((ROI_Calculations!$A$2:$A$121=A9)*(ROI_Calculations!$D$2:$D$121=B9)),ROI_Calculations!$I$2:$I$121))} -> 2.6394582 | G9: {=PERCENTILE(IF(((ROI_Calculations!$A$2:$A$121=A9)*(ROI_Calculations!$D$2:$D$121=B9)),ROI_Calculations!$I$2:$I$121),0.25)} -> 2.4319805 | H9: {=PERCENTILE(IF(((ROI_Calculations!$A$2:$A$121=A9)*(ROI_Calculations!$D$2:$D$121=B9)),ROI_Calculations!$I$2:$I$121),0.75)} -> 2.7609629 | I9: {=MEDIAN(IF(((ROI_Calculations!$A$2:$A$121=A9)*(ROI_Calculations!$D$2:$D$121=B9)),ROI_Calculations!$J$2:$J$121))} -> 89.434446 | J9: {=PERCENTILE(IF(((ROI_Calculations!$A$2:$A$121=A9)*(ROI_Calculations!$D$2:$D$121=B9)),ROI_Calculations!$J$2:$J$121),0.25)} -> 81.152039 | K9: {=PERCENTILE(IF(((ROI_Calculations!$A$2:$A$121=A9)*(ROI_Calculations!$D$2:$D$121=B9)),ROI_Calculations!$J$2:$J$121),0.75)} -> 105.6041 | L9: {=MEDIAN(IF(((ROI_Calculations!$A$2:$A$121=A9)*(ROI_Calculations!$D$2:$D$121=B9)),ROI_Calculations!$K$2:$K$121))} -> 278.86889 | M9: {=PERCENTILE(IF(((ROI_Calculations!$A$2:$A$121=A9)*(ROI_Calculations!$D$2:$D$121=B9)),ROI_Calculations!$K$2:$K$121),0.25)} -> 262.30408 | N9: {=PERCENTILE(IF(((ROI_Calculations!$A$2:$A$121=A9)*(ROI_Calculations!$D$2:$D$121=B9)),ROI_Calculations!$K$2:$K$121),0.75)} -> 311.20821
A10: Germany | B10: Data analyst | C10: {=MEDIAN(IF(((ROI_Calculations!$A$2:$A$121=A10)*(ROI_Calculations!$D$2:$D$121=B10)),ROI_Calculations!$H$2:$H$121))} -> 0 | D10: {=PERCENTILE(IF(((ROI_Calculations!$A$2:$A$121=A10)*(ROI_Calculations!$D$2:$D$121=B10)),ROI_Calculations!$H$2:$H$121),0.25)} -> 0 | E10: {=PERCENTILE(IF(((ROI_Calculations!$A$2:$A$121=A10)*(ROI_Calculations!$D$2:$D$121=B10)),ROI_Calculations!$H$2:$H$121),0.75)} -> 0.12358623 | F10: {=MEDIAN(IF(((ROI_Calculations!$A$2:$A$121=A10)*(ROI_Calculations!$D$2:$D$121=B10)),ROI_Calculations!$I$2:$I$121))} -> 0.7250826 | G10: {=PERCENTILE(IF(((ROI_Calculations!$A$2:$A$121=A10)*(ROI_Calculations!$D$2:$D$121=B10)),ROI_Calculations!$I$2:$I$121),0.25)} -> 0.66344925 | H10: {=PERCENTILE(IF(((ROI_Calculations!$A$2:$A$121=A10)*(ROI_Calculations!$D$2:$D$121=B10)),ROI_Calculations!$I$2:$I$121),0.75)} -> 0.846203 | I10: {=MEDIAN(IF(((ROI_Calculations!$A$2:$A$121=A10)*(ROI_Calculations!$D$2:$D$121=B10)),ROI_Calculations!$J$2:$J$121))} -> 589.57661 | J10: {=PERCENTILE(IF(((ROI_Calculations!$A$2:$A$121=A10)*(ROI_Calculations!$D$2:$D$121=B10)),ROI_Calculations!$J$2:$J$121),0.25)} -> 491.01335 | K10: {=PERCENTILE(IF(((ROI_Calculations!$A$2:$A$121=A10)*(ROI_Calculations!$D$2:$D$121=B10)),ROI_Calculations!$J$2:$J$121),0.75)} -> 654.09332 | L10: {=MEDIAN(IF(((ROI_Calculations!$A$2:$A$121=A10)*(ROI_Calculations!$D$2:$D$121=B10)),ROI_Calculations!$K$2:$K$121))} -> 1279.1532 | M10: {=PERCENTILE(IF(((ROI_Calculations!$A$2:$A$121=A10)*(ROI_Calculations!$D$2:$D$121=B10)),ROI_Calculations!$K$2:$K$121),0.25)} -> 1082.0267 | N10: {=PERCENTILE(IF(((ROI_Calculations!$A$2:$A$121=A10)*(ROI_Calculations!$D$2:$D$121=B10)),ROI_Calculations!$K$2:$K$121),0.75)} -> 1408.1866
A11: Germany | B11: Data scientist | C11: {=MEDIAN(IF(((ROI_Calculations!$A$2:$A$121=A11)*(ROI_Calculations!$D$2:$D$121=B11)),ROI_Calculations!$H$2:$H$121))} -> 0 | D11: {=PERCENTILE(IF(((ROI_Calculations!$A$2:$A$121=A11)*(ROI_Calculations!$D$2:$D$121=B11)),ROI_Calculations!$H$2:$H$121),0.25)} -> 0 | E11: {=PERCENTILE(IF(((ROI_Calculations!$A$2:$A$121=A11)*(ROI_Calculations!$D$2:$D$121=B11)),ROI_Calculations!$H$2:$H$121),0.75)} -> 0.11066184 | F11: {=MEDIAN(IF(((ROI_Calculations!$A$2:$A$121=A11)*(ROI_Calculations!$D$2:$D$121=B11)),ROI_Calculations!$I$2:$I$121))} -> 0.64925502 | G11: {=PERCENTILE(IF(((ROI_Calculations!$A$2:$A$121=A11)*(ROI_Calculations!$D$2:$D$121=B11)),ROI_Calculations!$I$2:$I$121),0.25)} -> 0.59406716 | H11: {=PERCENTILE(IF(((ROI_Calculations!$A$2:$A$121=A11)*(ROI_Calculations!$D$2:$D$121=B11)),ROI_Calculations!$I$2:$I$121),0.75)} -> 0.75770892 | I11: {=MEDIAN(IF(((ROI_Calculations!$A$2:$A$121=A11)*(ROI_Calculations!$D$2:$D$121=B11)),ROI_Calculations!$J$2:$J$121))} -> 670.11341 | J11: {=PERCENTILE(IF(((ROI_Calculations!$A$2:$A$121=A11)*(ROI_Calculations!$D$2:$D$121=B11)),ROI_Calculations!$J$2:$J$121),0.25)} -> 560.03879 | K11: {=PERCENTILE(IF(((ROI_Calculations!$A$2:$A$121=A11)*(ROI_Calculations!$D$2:$D$121=B11)),ROI_Calculations!$J$2:$J$121),0.75)} -> 742.16514 | L11: {=MEDIAN(IF(((ROI_Calculations!$A$2:$A$121=A11)*(ROI_Calculations!$D$2:$D$121=B11)),ROI_Calculations!$K$2:$K$121))} -> 1440.2268 | M11: {=PERCENTILE(IF(((ROI_Calculations!$A$2:$A$121=A11)*(ROI_Calculations!$D$2:$D$121=B11)),ROI_Calculations!$K$2:$K$121),0.25)} -> 1220.0776 | N11: {=PERCENTILE(IF(((ROI_Calculations!$A$2:$A$121=A11)*(ROI_Calculations!$D$2:$D$121=B11)),ROI_Calculations!$K$2:$K$121),0.75)} -> 1584.3303
A12: Netherlands | B12: Data analyst | C12: {=MEDIAN(IF(((ROI_Calculations!$A$2:$A$121=A12)*(ROI_Calculations!$D$2:$D$121=B12)),ROI_Calculations!$H$2:$H$121))} -> 1.1805107 | D12: {=PERCENTILE(IF(((ROI_Calculations!$A$2:$A$121=A12)*(ROI_Calculations!$D$2:$D$121=B12)),ROI_Calculations!$H$2:$H$121),0.25)} -> 0.8056922 | E12: {=PERCENTILE(IF(((ROI_Calculations!$A$2:$A$121=A12)*(ROI_Calculations!$D$2:$D$121=B12)),ROI_Calculations!$H$2:$H$121),0.75)} -> 1.2665613 | F12: {=MEDIAN(IF(((ROI_Calculations!$A$2:$A$121=A12)*(ROI_Calculations!$D$2:$D$121=B12)),ROI_Calculations!$I$2:$I$121))} -> 1.9430897 | G12: {=PERCENTILE(IF(((ROI_Calculations!$A$2:$A$121=A12)*(ROI_Calculations!$D$2:$D$121=B12)),ROI_Calculations!$I$2:$I$121),0.25)} -> 1.2932303 | H12: {=PERCENTILE(IF(((ROI_Calculations!$A$2:$A$121=A12)*(ROI_Calculations!$D$2:$D$121=B12)),ROI_Calculations!$I$2:$I$121),0.75)} -> 2.0859276 | I12: {=MEDIAN(IF(((ROI_Calculations!$A$2:$A$121=A12)*(ROI_Calculations!$D$2:$D$121=B12)),ROI_Calculations!$J$2:$J$121))} -> 157.42196 | J12: {=PERCENTILE(IF(((ROI_Calculations!$A$2:$A$121=A12)*(ROI_Calculations!$D$2:$D$121=B12)),ROI_Calculations!$J$2:$J$121),0.25)} -> 139.85019 | K12: {=PERCENTILE(IF(((ROI_Calculations!$A$2:$A$121=A12)*(ROI_Calculations!$D$2:$D$121=B12)),ROI_Calculations!$J$2:$J$121),0.75)} -> 300.84608 | L12: {=MEDIAN(IF(((ROI_Calculations!$A$2:$A$121=A12)*(ROI_Calculations!$D$2:$D$121=B12)),ROI_Calculations!$K$2:$K$121))} -> 414.84393 | M12: {=PERCENTILE(IF(((ROI_Calculations!$A$2:$A$121=A12)*(ROI_Calculations!$D$2:$D$121=B12)),ROI_Calculations!$K$2:$K$121),0.25)} -> 379.70037 | N12: {=PERCENTILE(IF(((ROI_Calculations!$A$2:$A$121=A12)*(ROI_Calculations!$D$2:$D$121=B12)),ROI_Calculations!$K$2:$K$121),0.75)} -> 701.69217
A13: Netherlands | B13: Data scientist | C13: {=MEDIAN(IF(((ROI_Calculations!$A$2:$A$121=A13)*(ROI_Calculations!$D$2:$D$121=B13)),ROI_Calculations!$H$2:$H$121))} -> 1.0015103 | D13: {=PERCENTILE(IF(((ROI_Calculations!$A$2:$A$121=A13)*(ROI_Calculations!$D$2:$D$121=B13)),ROI_Calculations!$H$2:$H$121),0.25)} -> 0.68352544 | E13: {=PERCENTILE(IF(((ROI_Calculations!$A$2:$A$121=A13)*(ROI_Calculations!$D$2:$D$121=B13)),ROI_Calculations!$H$2:$H$121),0.75)} -> 1.0745131 | F13: {=MEDIAN(IF(((ROI_Calculations!$A$2:$A$121=A13)*(ROI_Calculations!$D$2:$D$121=B13)),ROI_Calculations!$I$2:$I$121))} -> 1.6484599 | G13: {=PERCENTILE(IF(((ROI_Calculations!$A$2:$A$121=A13)*(ROI_Calculations!$D$2:$D$121=B13)),ROI_Calculations!$I$2:$I$121),0.25)} -> 1.0971383 | H13: {=PERCENTILE(IF(((ROI_Calculations!$A$2:$A$121=A13)*(ROI_Calculations!$D$2:$D$121=B13)),ROI_Calculations!$I$2:$I$121),0.75)} -> 1.7696393 | I13: {=MEDIAN(IF(((ROI_Calculations!$A$2:$A$121=A13)*(ROI_Calculations!$D$2:$D$121=B13)),ROI_Calculations!$J$2:$J$121))} -> 203.43109 | J13: {=PERCENTILE(IF(((ROI_Calculations!$A$2:$A$121=A13)*(ROI_Calculations!$D$2:$D$121=B13)),ROI_Calculations!$J$2:$J$121),0.25)} -> 182.7187 | K13: {=PERCENTILE(IF(((ROI_Calculations!$A$2:$A$121=A13)*(ROI_Calculations!$D$2:$D$121=B13)),ROI_Calculations!$J$2:$J$121),0.75)} -> 372.48946 | L13: {=MEDIAN(IF(((ROI_Calculations!$A$2:$A$121=A13)*(ROI_Calculations!$D$2:$D$121=B13)),ROI_Calculations!$K$2:$K$121))} -> 506.86218 | M13: {=PERCENTILE(IF(((ROI_Calculations!$A$2:$A$121=A13)*(ROI_Calculations!$D$2:$D$121=B13)),ROI_Calculations!$K$2:$K$121),0.25)} -> 465.4374 | N13: {=PERCENTILE(IF(((ROI_Calculations!$A$2:$A$121=A13)*(ROI_Calculations!$D$2:$D$121=B13)),ROI_Calculations!$K$2:$K$121),0.75)} -> 844.97891
